Billaume/TP4/registre.vhd
--Entite add
library IEEE;
use IEEE.std_logic_1164.all;

--definition de l'entite
entity registre is
	generic(
		N : natural
	);

	port(
		D : in std_logic_vector(N-1 downto 0);
		clk : in std_logic;
		load : in std_logic;
		nrst : in std_logic;
		Q : out std_logic_vector(N-1 downto 0)

	);
end entity;

--definition de l'architecture
architecture flot of registre is
begin
	update: process(clk,nrst)
	begin
		if(nrst = '0') then
			Q <= (others =>'0');
		elsif(clk'event and  clk = '1' and load = '1') then
			Q<=D;
		end if;
	end process;
		
end architecture;

Billaume/TP3/add.vhd
--Entite add
library IEEE;
use IEEE.std_logic_1164.all;

--definition de l'entite
entity add is
	port(
		A : in std_logic;
		B : in std_logic;
		Cin : in std_logic;
		S : out std_logic;
		Cout : out std_logic
	);
end entity;

--definition de l'architecture
architecture flot of add is
begin
	S <= A xor B xor Cin;
	Cout <= (A and B) or (A and Cin) or (B and Cin);
end architecture;

Billaume/TP2/incrementeur.vhd
--Entite add
library IEEE;
use IEEE.std_logic_1164.all;

--definition de l'entite
entity incrementeur is
	generic(
		N : natural
	);

	port(
		X : in std_logic_vector(N-1 downto 0);
		S : out std_logic_vector(N-1 downto 0);
		R : out std_logic
	);
end entity;

--definition de l'architecture
architecture flot of incrementeur is

component add is
	port(
		A : in std_logic;
		B : in std_logic;
		Cin : in std_logic;
		S : out std_logic;
		Cout : out std_logic
	);
end component;

signal carry : std_logic_vector(N downto 0);
signal incr_c : std_logic_vector(N downto 0);
begin
	incr_c(0) <= '1';
	carry(0) <= '0';
	incrementeur_inst : for i in N-1 downto 0 generate

	add_inst : add
		port map(A=>X(i),
		B=> incr_c(i),
		Cin => carry(i), 
		S => S(i),
		Cout => Carry(i+1));
	incr_c(i+1) <= '0';
	end generate;
	R <= carry(N);
	
end architecture;

Billaume/TP2/multiplexeur.vhd
--Entite add
library IEEE;
use IEEE.std_logic_1164.all;

--definition de l'entite
entity multiplexeur is
	port(
		D0 : in integer;
		D1 : in integer;
		sel : in std_logic;
		S : out integer

	);
end entity;

--definition de l'architecture
architecture flot of multiplexeur is
begin
	S <= D0 when sel = '0' else D1;
end architecture;

Billaume/TP4/LoadCount.vhd
--Entite add
library IEEE;
use IEEE.std_logic_1164.all;

--definition de l'entite
entity LoadCount is
	generic(
		N : natural
	);

	port(
		X : in std_logic_vector(N-1 downto 0);
		clk : in std_logic;
		st : in std_logic;
		nrst : in std_logic;
		S : out std_logic_vector(N-1 downto 0)
	);
end entity;

--definition de l'architecture
architecture flot of LoadCount is

signal IncrOutput : std_logic_vector(N-1 downto 0);
signal MuxInOutput : std_logic_vector(N-1 downto 0);
signal RegistreOut : std_logic_vector(N-1 downto 0);
signal load : std_logic;

component incrementeur is
	generic(
		N : natural
	);

	port(
		X : in std_logic_vector(N-1 downto 0);
		S : out std_logic_vector(N-1 downto 0);
		R : out std_logic
	);
end component;

component multiplexeur is
	generic(
		N : natural
	);
	port(
		D0 : in std_logic_vector(N-1 downto 0);
		D1 : in std_logic_vector(N-1 downto 0);
		sel : in std_logic;
		S : out std_logic_vector(N-1 downto 0)
	);
end component;

component registre is
	generic(
		N : natural
	);

	port(
		D : in std_logic_vector(N-1 downto 0);
		clk : in std_logic;
		load : in std_logic;
		nrst : in std_logic;
		Q : out std_logic_vector(N-1 downto 0)

	);
end component;
	

begin

load <= not (st and '0');
	
	Mul : multiplexeur
	generic map(N=>N)
	port map(
		D0 => IncrOutput,
		D1 => X,
		sel => st,
		S => MuxInOutput
		);

	incr : incrementeur
	generic map(N=>N)
	port map(
		X => RegistreOut,
		S => IncrOutput
		);

	reg: registre
	generic map(N=>N)
	port map(
		D => MuxInOutput,
		clk => clk,
		load => load,
		nrst => nrst,
		Q => RegistreOut
		);

		S <= RegistreOut;
	
end architecture;

Billaume/TP3/Bench_LoadCount/bench_LoadCount.vhd
library IEEE;
use     IEEE.std_logic_1164.all;
use     IEEE.numeric_std.all;


-- bibliotheque indique dans votre Makefile
library TP_LIB;
use     TP_LIB.LoadCount;

entity bench_LoadCount is

end entity;

architecture str of bench_LoadCount is

	component LoadCount is
		generic(
			N : natural
		);

		port(
			X : in std_logic_vector(N-1 downto 0);
			clk : in std_logic;
			st : in std_logic;
			nrst : in std_logic;
			S : out std_logic_vector(N-1 downto 0)
		);
	end component;
	
	constant N_c : natural := 4;
	
	-- definition de signaux de test	
	signal X_S : std_logic_vector(N_c-1 downto 0):= "0011";
	
	--selection
	signal SEL_S : std_logic:='0';
	signal clk_S : std_logic:='0';
	signal nrst_S : std_logic:='1';
	-- sortie des composant
	signal SORTIE_S : std_logic_vector(N_c-1 downto 0);



begin
	LoadCount_test : LoadCount
		generic map(
		N => N_c)
		
		port map(
		X => X_S,
		clk => clk_S,
		st => SEL_S,
		nrst =>nrst_S,
		S => SORTIE_S
		);
		
	clk_S <= not clk_S after 2 ns;
	SEL_S <= '1' after 7 ns, '0' after 12 ns, '1' after 50 ns, '0' after 55 ns;
	nrst_S <= '0' after 80 ns, '1' after 82 ns;

end architecture;

Billaume/TP3/Bench_LoadCount/bench_LoadCount_wave.vcd
$date
  Mon Nov 30 15:41:32 2020
$end
$version
  GHDL v0
$end
$timescale
  1 fs
$end
$scope module standard $end
$upscope $end
$scope module std_logic_1164 $end
$upscope $end
$scope module numeric_std $end
$upscope $end
$scope module bench_loadcount $end
$var reg 4 ! x_s[3:0] $end
$var reg 1 " sel_s $end
$var reg 1 # clk_s $end
$var reg 1 $ nrst_s $end
$var reg 4 % sortie_s[3:0] $end
$scope module loadcount_test $end
$var reg 4 & x[3:0] $end
$var reg 1 ' clk $end
$var reg 1 ( st $end
$var reg 1 ) nrst $end
$var reg 4 * s[3:0] $end
$var reg 4 + incroutput[3:0] $end
$var reg 4 , muxinoutput[3:0] $end
$var reg 4 - registreout[3:0] $end
$var reg 1 . load $end
$scope module mul $end
$var reg 4 / d0[3:0] $end
$var reg 4 0 d1[3:0] $end
$var reg 1 1 sel $end
$var reg 4 2 s[3:0] $end
$upscope $end
$scope module incr $end
$var reg 4 3 x[3:0] $end
$var reg 4 4 s[3:0] $end
$var reg 1 5 r $end
$var reg 5 6 carry[4:0] $end
$var reg 5 7 incr_c[4:0] $end
$scope module incrementeur_inst(0) $end
$scope module add_inst $end
$var reg 1 8 a $end
$var reg 1 9 b $end
$var reg 1 : cin $end
$var reg 1 ; s $end
$var reg 1 < cout $end
$upscope $end
$upscope $end
$scope module incrementeur_inst(1) $end
$scope module add_inst $end
$var reg 1 = a $end
$var reg 1 > b $end
$var reg 1 ? cin $end
$var reg 1 @ s $end
$var reg 1 A cout $end
$upscope $end
$upscope $end
$scope module incrementeur_inst(2) $end
$scope module add_inst $end
$var reg 1 B a $end
$var reg 1 C b $end
$var reg 1 D cin $end
$var reg 1 E s $end
$var reg 1 F cout $end
$upscope $end
$upscope $end
$scope module incrementeur_inst(3) $end
$scope module add_inst $end
$var reg 1 G a $end
$var reg 1 H b $end
$var reg 1 I cin $end
$var reg 1 J s $end
$var reg 1 K cout $end
$upscope $end
$upscope $end
$upscope $end
$scope module reg $end
$var reg 4 L d[3:0] $end
$var reg 1 M clk $end
$var reg 1 N load $end
$var reg 1 O nrst $end
$var reg 4 P q[3:0] $end
$upscope $end
$upscope $end
$upscope $end
$enddefinitions $end
#0
b0011 !
0"
0#
1$
bUUUU %
b0011 &
0'
0(
1)
bUUUU *
bUUUU +
bUUUU ,
bUUUU -
1.
bUUUU /
b0011 0
01
bUUUU 2
bUUUU 3
bUUUU 4
U5
bUUUU0 6
b00001 7
U8
19
0:
U;
U<
U=
0>
U?
U@
UA
UB
0C
UD
UE
UF
UG
0H
UI
UJ
UK
bUUUU L
0M
1N
1O
bUUUU P
#2000000
1#
1'
1M
#4000000
0#
0'
0M
#6000000
1#
1'
1M
#7000000
1"
1(
b0011 ,
11
b0011 2
b0011 L
#8000000
0#
0'
0M
#10000000
1#
b0011 %
1'
b0011 *
b0100 +
b0011 -
b0100 /
b0011 3
b0100 4
05
b00110 6
18
0;
1<
1=
1?
0@
1A
0B
1D
1E
0F
0G
0I
0J
0K
1M
b0011 P
#12000000
0"
0#
0'
0(
b0100 ,
01
b0100 2
b0100 L
0M
#14000000
1#
b0100 %
1'
b0100 *
b0101 +
b0101 ,
b0100 -
b0101 /
b0101 2
b0100 3
b0101 4
b00000 6
08
1;
0<
0=
0?
0@
0A
1B
0D
1E
0F
0I
0J
b0101 L
1M
b0100 P
#16000000
0#
0'
0M
#18000000
1#
b0101 %
1'
b0101 *
b0110 +
b0110 ,
b0101 -
b0110 /
b0110 2
b0101 3
b0110 4
b00010 6
18
0;
1<
1?
1@
b0110 L
1M
b0101 P
#20000000
0#
0'
0M
#22000000
1#
b0110 %
1'
b0110 *
b0111 +
b0111 ,
b0110 -
b0111 /
b0111 2
b0110 3
b0111 4
b00000 6
08
1;
0<
1=
0?
1@
0A
0D
1E
0F
0I
0J
b0111 L
1M
b0110 P
#24000000
0#
0'
0M
#26000000
1#
b0111 %
1'
b0111 *
b1000 +
b1000 ,
b0111 -
b1000 /
b1000 2
b0111 3
b1000 4
b01110 6
18
0;
1<
1?
0@
1A
1D
0E
1F
1I
1J
b1000 L
1M
b0111 P
#28000000
0#
0'
0M
#30000000
1#
b1000 %
1'
b1000 *
b1001 +
b1001 ,
b1000 -
b1001 /
b1001 2
b1000 3
b1001 4
05
b00000 6
08
1;
0<
0=
0?
0@
0A
0B
0D
0E
0F
1G
0I
1J
0K
b1001 L
1M
b1000 P
#32000000
0#
0'
0M
#34000000
1#
b1001 %
1'
b1001 *
b1010 +
b1010 ,
b1001 -
b1010 /
b1010 2
b1001 3
b1010 4
b00010 6
18
0;
1<
1?
1@
b1010 L
1M
b1001 P
#36000000
0#
0'
0M
#38000000
1#
b1010 %
1'
b1010 *
b1011 +
b1011 ,
b1010 -
b1011 /
b1011 2
b1010 3
b1011 4
b00000 6
08
1;
0<
1=
0?
1@
0A
0D
0E
b1011 L
1M
b1010 P
#40000000
0#
0'
0M
#42000000
1#
b1011 %
1'
b1011 *
b1100 +
b1100 ,
b1011 -
b1100 /
b1100 2
b1011 3
b1100 4
b00110 6
18
0;
1<
1?
0@
1A
1D
1E
b1100 L
1M
b1011 P
#44000000
0#
0'
0M
#46000000
1#
b1100 %
1'
b1100 *
b1101 +
b1101 ,
b1100 -
b1101 /
b1101 2
b1100 3
b1101 4
05
b00000 6
08
1;
0<
0=
0?
0@
0A
1B
0D
1E
0F
0I
1J
0K
b1101 L
1M
b1100 P
#48000000
0#
0'
0M
#50000000
1"
1#
b1101 %
1'
1(
b1101 *
b1110 +
b0011 ,
b1101 -
b1110 /
11
b0011 2
b1101 3
b1110 4
b00010 6
18
0;
1<
1?
1@
b0011 L
1M
b1101 P
#52000000
0#
0'
0M
#54000000
1#
b0011 %
1'
b0011 *
b0100 +
b0011 -
b0100 /
b0011 3
b0100 4
b00110 6
1=
0@
1A
0B
1D
1E
0G
0J
1M
b0011 P
#55000000
0"
0(
b0100 ,
01
b0100 2
b0100 L
#56000000
0#
0'
0M
#58000000
1#
b0100 %
1'
b0100 *
b0101 +
b0101 ,
b0100 -
b0101 /
b0101 2
b0100 3
b0101 4
b00000 6
08
1;
0<
0=
0?
0@
0A
1B
0D
1E
0F
0I
0J
b0101 L
1M
b0100 P
#60000000
0#
0'
0M
#62000000
1#
b0101 %
1'
b0101 *
b0110 +
b0110 ,
b0101 -
b0110 /
b0110 2
b0101 3
b0110 4
b00010 6
18
0;
1<
1?
1@
b0110 L
1M
b0101 P
#64000000
0#
0'
0M
#66000000
1#
b0110 %
1'
b0110 *
b0111 +
b0111 ,
b0110 -
b0111 /
b0111 2
b0110 3
b0111 4
b00000 6
08
1;
0<
1=
0?
1@
0A
0D
1E
0F
0I
0J
b0111 L
1M
b0110 P
#68000000
0#
0'
0M
#70000000
1#
b0111 %
1'
b0111 *
b1000 +
b1000 ,
b0111 -
b1000 /
b1000 2
b0111 3
b1000 4
b01110 6
18
0;
1<
1?
0@
1A
1D
0E
1F
1I
1J
b1000 L
1M
b0111 P
#72000000
0#
0'
0M
#74000000
1#
b1000 %
1'
b1000 *
b1001 +
b1001 ,
b1000 -
b1001 /
b1001 2
b1000 3
b1001 4
05
b00000 6
08
1;
0<
0=
0?
0@
0A
0B
0D
0E
0F
1G
0I
1J
0K
b1001 L
1M
b1000 P
#76000000
0#
0'
0M
#78000000
1#
b1001 %
1'
b1001 *
b1010 +
b1010 ,
b1001 -
b1010 /
b1010 2
b1001 3
b1010 4
b00010 6
18
0;
1<
1?
1@
b1010 L
1M
b1001 P
#80000000
0#
0$
b0000 %
0'
0)
b0000 *
b0001 +
b0001 ,
b0000 -
b0001 /
b0001 2
b0000 3
b0001 4
b00000 6
08
1;
0<
0?
0@
0G
0J
b0001 L
0M
0O
b0000 P
#82000000
1#
1$
b0001 %
1'
1)
b0001 *
b0010 +
b0010 ,
b0001 -
b0010 /
b0010 2
b0001 3
b0010 4
b00010 6
18
0;
1<
1?
1@
b0010 L
1M
1O
b0001 P
#84000000
0#
0'
0M
#86000000
1#
b0010 %
1'
b0010 *
b0011 +
b0011 ,
b0010 -
b0011 /
b0011 2
b0010 3
b0011 4
b00000 6
08
1;
0<
1=
0?
1@
0A
0D
0E
b0011 L
1M
b0010 P
#88000000
0#
0'
0M
#90000000
1#
b0011 %
1'
b0011 *
b0100 +
b0100 ,
b0011 -
b0100 /
b0100 2
b0011 3
b0100 4
b00110 6
18
0;
1<
1?
0@
1A
1D
1E
b0100 L
1M
b0011 P
#92000000
0#
0'
0M
#94000000
1#
b0100 %
1'
b0100 *
b0101 +
b0101 ,
b0100 -
b0101 /
b0101 2
b0100 3
b0101 4
b00000 6
08
1;
0<
0=
0?
0@
0A
1B
0D
1E
0F
0I
0J
b0101 L
1M
b0100 P
#96000000
0#
0'
0M
#98000000
1#
b0101 %
1'
b0101 *
b0110 +
b0110 ,
b0101 -
b0110 /
b0110 2
b0101 3
b0110 4
b00010 6
18
0;
1<
1?
1@
b0110 L
1M
b0101 P
