Billaume/TP4/registre.vhd
--Entite add
library IEEE;
use IEEE.std_logic_1164.all;

--definition de l'entite
entity registre is
	generic(
		N : natural
	);

	port(
		D : in std_logic_vector(N-1 downto 0);
		clk : in std_logic;
		load : in std_logic;
		nrst : in std_logic;
		Q : out std_logic_vector(N-1 downto 0)

	);
end entity;

--definition de l'architecture
architecture flot of registre is
begin
	update: process(clk,nrst)
	begin
		if(nrst = '0') then
			Q <= (others =>'0');
		elsif(clk'event and  clk = '1' and load = '1') then
			Q<=D;
		end if;
	end process;
		
end architecture;

Billaume/TP2/Bench_registre/bench_registre.vhd
--Aiguillage téléphonique
library IEEE;
use IEEE.std_logic_1164.all;
use IEEE.numeric_std.all;

--bibliotheque indique dans votre Makefile
library TP_LIB;
use     TP_LIB.registre;

--definition de l'entite
entity bench_registre is
end entity;

--definition de l'architecture de test
architecture test of bench_registre is

  component registre
	generic(
		N : natural
	);

	port(
		D : in std_logic_vector(N-1 downto 0);
		clk : in std_logic;
		load : in std_logic;
		nrst : in std_logic;
		Q : out std_logic_vector(N-1 downto 0)

	);
  end component;

  constant N_c : natural := 4;
  --definition de signaux de test
  signal load_S : std_logic := '0' ;
  signal nrst_S : std_logic := '1' ;
  signal clk_S : std_logic := '0' ;
  signal D_S : std_logic_vector(N_c-1 downto 0) := "1010";
  signal Q_S : std_logic_vector(N_c-1 downto 0);

  

begin

  --design under test (dut)
  dut : registre
    generic map(
    N => N_c)
    port map(
      D => D_S,
      clk => clk_S,
      Q => Q_S,
      load => load_S,
      nrst => nrst_S
      
    );

  --Generation des stimulis
  
  clk_S <=  not clk_S after 5 ns;
  nrst_S <= not nrst_S after 35 ns, '1' after 40 ns;
  load_S <= not load_S after 30 ns, '0' after 35 ns; 
  
end architecture;

Billaume/TP2/Bench_registre/bench_registre_wave.vcd
$date
  Tue Nov 17 16:00:21 2020
$end
$version
  GHDL v0
$end
$timescale
  1 fs
$end
$scope module standard $end
$upscope $end
$scope module std_logic_1164 $end
$upscope $end
$scope module numeric_std $end
$upscope $end
$scope module bench_registre $end
$var reg 1 ! load_s $end
$var reg 1 " nrst_s $end
$var reg 1 # clk_s $end
$var reg 4 $ d_s[3:0] $end
$var reg 4 % q_s[3:0] $end
$scope module dut $end
$var reg 4 & d[3:0] $end
$var reg 1 ' clk $end
$var reg 1 ( load $end
$var reg 1 ) nrst $end
$var reg 4 * q[3:0] $end
$upscope $end
$upscope $end
$enddefinitions $end
#0
0!
1"
0#
b1010 $
bUUUU %
b1010 &
0'
0(
1)
bUUUU *
#5000000
1#
1'
#10000000
0#
0'
#15000000
1#
1'
#20000000
0#
0'
#25000000
1#
1'
#30000000
1!
0#
0'
1(
#35000000
0!
0"
1#
b0000 %
1'
0(
0)
b0000 *
#40000000
1"
0#
0'
1)
#45000000
1#
1'
#50000000
0#
0'
#55000000
1#
1'
#60000000
0#
0'
#65000000
1!
1#
b1010 %
1'
1(
b1010 *
#70000000
0!
0#
0'
0(
#75000000
0"
1#
b0000 %
1'
0)
b0000 *
#80000000
1"
0#
0'
1)
#85000000
1#
1'
#90000000
0#
0'
#95000000
1#
1'
#100000000
1!
0#
0'
1(
