Billaume/TP3/RAM.vhd
library IEEE;
use IEEE.std_logic_textio.all;
use IEEE.std_logic_1164.all;
use IEEE.std_logic_unsigned.all;
use IEEE.std_logic_arith.all;
use std.textio.all;

entity RAM is
	generic(
		load_file_name : string;
		dta : integer := 8;
		adr : integer := 4);
		
	port(
		address : in std_logic_vector(adr-1 downto 0);
		datain : in std_logic_vector(dta-1 downto 0);
		wr_ena : in std_logic;
		dataout : out std_logic_vector(dta-1 downto 0));
end RAM;

architecture beh of RAM is
	begin
		p_init_mem : process
			subtype myword is std_logic_vector(0 to datain'length-1);
			type storage_array is
				array ( natural range 0 to 2**address'length-1) of myword;
		
			variable storage : storage_array;
			variable index : natural;
			variable mem_data : line;
			variable vdata : integer;
			file load_file : text is load_file_name;
		
			begin
				index := 0;
				while not endfile(load_file) loop
					readline(load_file, mem_data);
					if mem_data'length > 0 then
						read(mem_data, vdata);
						storage(index):= std_logic_vector(conv_unsigned(vdata,datain'length));
						index := index +1;
					end if;
					if(index = 2**address'length) then
						index :=0;
					end if;
				end loop;
			
				loop
				 wait on address,wr_ena,datain;
				 	if wr_ena = '0' then
				 		index := conv_integer(unsigned(address));
				 		dataout <= std_logic_vector(storage(index));
			 		else
			 			index :=conv_integer(unsigned(address));
			 			storage(index) := datain;
		 			end if;
 				end loop;
		end process;
end beh;

Billaume/TP4/registre.vhd
--Entite add
library IEEE;
use IEEE.std_logic_1164.all;

--definition de l'entite
entity registre is
	generic(
		N : natural
	);

	port(
		D : in std_logic_vector(N-1 downto 0);
		clk : in std_logic;
		load : in std_logic;
		nrst : in std_logic;
		Q : out std_logic_vector(N-1 downto 0)

	);
end entity;

--definition de l'architecture
architecture flot of registre is
begin
	update: process(clk,nrst)
	begin
		if(nrst = '0') then
			Q <= (others =>'0');
		elsif(clk'event and  clk = '1' and load = '1') then
			Q<=D;
		end if;
	end process;
		
end architecture;

Billaume/TP4/MemREGs.vhd
library IEEE;
use IEEE.std_logic_textio.all;
use IEEE.std_logic_1164.all;
use IEEE.std_logic_unsigned.all;
use IEEE.std_logic_arith.all;
use std.textio.all;

entity MemREGs is
	generic(
		load_file_name : string;
		dta : integer := 8;
		adr : integer := 4);	
	port(
		Xin : in std_logic_vector(dta-1 downto 0);
		a : in std_logic;
		d : in std_logic;
		sa  : in std_logic;
		clk : in std_logic;
		Reset : in std_logic;
		Aout : out std_logic_vector(adr-1 downto 0);
		Dout : out std_logic_vector(adr-1 downto 0);
		FromMem : out std_logic_vector(dta-1 downto 0));
	
end entity;

architecture beh of MemREGs is


signal RegistreDOut : std_logic_vector(adr-1 downto 0);
signal RegistreAOut : std_logic_vector(adr-1 downto 0);
signal RamOut : std_logic_vector(dta-1 downto 0);

		
component registre is
	generic(
		N : natural
	);

	port(
		D : in std_logic_vector(N-1 downto 0);
		clk : in std_logic;
		load : in std_logic;
		nrst : in std_logic;
		Q : out std_logic_vector(N-1 downto 0)

	);
end component;

component RAM is
	generic(
		load_file_name : string;
		dta : integer := 8;
		adr : integer := 4);
		
	port(
		address : in std_logic_vector(adr-1 downto 0);
		datain : in std_logic_vector(dta-1 downto 0);
		wr_ena : in std_logic;
		dataout : out std_logic_vector(dta-1 downto 0));
end component;

begin

	regA: registre
	generic map(N=>adr)
	port map(
		D => Xin,
		clk => clk,
		load => a,
		nrst => Reset,
		Q => RegistreAOut
		);
		
	regD: registre
	generic map(N=>adr)
	port map(
		D => Xin,
		clk => clk,
		load => d,
		nrst => Reset,
		Q => RegistreDOut
		);

	ROM : RAM
	generic map
	(load_file_name=>load_file_name,
	dta => dta,
	adr => adr)

	port map(
		address => RegistreAOut,
		datain => Xin,
		wr_ena => sa,
		dataout => RamOut
		);
		
	Aout <= RegistreAOut;
	Dout <= RegistreDOut;
	FromMem <= RamOut;

end beh;

Billaume/TP4/Bench_MemREGs/bench_MemREGs.vhd
library ieee;
use ieee.std_logic_textio.all;
use ieee.std_logic_1164.all;
use ieee.std_logic_unsigned.all;
use ieee.std_logic_arith.all;
use std.textio.all;


-- bibliotheque indique dans votre Makefile
library TP_LIB;
use     TP_LIB.MemREGs;

entity bench_MemREGs is

end entity;

architecture str of bench_MemREGs is

	component MemREGs is
		generic(
			load_file_name : string;
			dta : integer := 8;
			adr : integer := 4);	
		port(
			Xin : in std_logic_vector(dta-1 downto 0);
			a : in std_logic;
			d : in std_logic;
			sa  : in std_logic;
			clk : in std_logic;
			Reset : in std_logic;
			Aout : out std_logic_vector(dta-1 downto 0);
			Dout : out std_logic_vector(dta-1 downto 0);
			FromMem : out std_logic_vector(dta-1 downto 0));
	end component;
	
	constant load_file_name_C : string := "monFichier.txt";
	constant dta_c : integer := 8;
	constant adr_c : integer := 8;
	
	-- definition de signaux de test	
	signal Xin_S : std_logic_vector(dta_c-1 downto 0):= "00011111";
	signal a_S : std_logic := '0';
	signal d_S : std_logic := '0';
	signal sa_S : std_logic := '0';
	signal clk_S : std_logic := '0';
	signal reset_S : std_logic := '0';
	
	-- sortie des composant
	signal FromMem_S : std_logic_vector(dta_c-1 downto 0);
	signal Aout_S : std_logic_vector(adr_c-1 downto 0);
	signal Dout_S : std_logic_vector(adr_c-1 downto 0);


begin
	MemRegs_test : MemREGs
		generic map(
		load_file_name => load_file_name_C,
		dta => dta_C,
		adr => adr_C)
		
		port map(
			Xin => Xin_S ,
			a => a_S ,
			d => d_S ,
			sa => sa_S ,
			clk => clk_S ,
			Reset => reset_S  ,
			Aout => Aout_S,
			Dout => Dout_S ,
			FromMem => FromMem_S
	
		);
		
	reset_S <= '1' after 15 ns, '0' after 50 ns , '1' after 52 ns;
	clk_S <= not clk_S after 2 ns;
	sa_S <= '1' after 40 ns , '0' after 45 ns, '1' after 80 ns, '0' after 85 ns;
	a_S <= '1' after 20 ns , '0' after 25 ns, '1' after 80 ns, '0' after 85 ns;
	d_S <= '1' after 30 ns , '0' after 35 ns, '1' after 80 ns, '0' after 85 ns;
	Xin_S <= "00000010" after 10 ns, "00000110" after 60 ns;
	

	

end architecture;

Billaume/TP4/Bench_MemREGs/bench_MemREGs_wave.vcd
$date
  Mon Dec 14 16:35:36 2020
$end
$version
  GHDL v0
$end
$timescale
  1 fs
$end
$scope module standard $end
$upscope $end
$scope module textio $end
$upscope $end
$scope module std_logic_1164 $end
$upscope $end
$scope module std_logic_textio $end
$upscope $end
$scope module std_logic_arith $end
$upscope $end
$scope module std_logic_unsigned $end
$upscope $end
$scope module bench_memregs $end
$var reg 8 ! xin_s[7:0] $end
$var reg 1 " a_s $end
$var reg 1 # d_s $end
$var reg 1 $ sa_s $end
$var reg 1 % clk_s $end
$var reg 1 & reset_s $end
$var reg 8 ' frommem_s[7:0] $end
$var reg 8 ( aout_s[7:0] $end
$var reg 8 ) dout_s[7:0] $end
$scope module memregs_test $end
$var reg 8 * xin[7:0] $end
$var reg 1 + a $end
$var reg 1 , d $end
$var reg 1 - sa $end
$var reg 1 . clk $end
$var reg 1 / reset $end
$var reg 8 0 aout[7:0] $end
$var reg 8 1 dout[7:0] $end
$var reg 8 2 frommem[7:0] $end
$var reg 8 3 registredout[7:0] $end
$var reg 8 4 registreaout[7:0] $end
$var reg 8 5 ramout[7:0] $end
$scope module rega $end
$var reg 8 6 d[7:0] $end
$var reg 1 7 clk $end
$var reg 1 8 load $end
$var reg 1 9 nrst $end
$var reg 8 : q[7:0] $end
$upscope $end
$scope module regd $end
$var reg 8 ; d[7:0] $end
$var reg 1 < clk $end
$var reg 1 = load $end
$var reg 1 > nrst $end
$var reg 8 ? q[7:0] $end
$upscope $end
$scope module rom $end
$var reg 8 @ address[7:0] $end
$var reg 8 A datain[7:0] $end
$var reg 1 B wr_ena $end
$var reg 8 C dataout[7:0] $end
$upscope $end
$upscope $end
$upscope $end
$enddefinitions $end
#0
b00011111 !
0"
0#
0$
0%
0&
b00001010 '
b00000000 (
b00000000 )
b00011111 *
0+
0,
0-
0.
0/
b00000000 0
b00000000 1
b00001010 2
b00000000 3
b00000000 4
b00001010 5
b00011111 6
07
08
09
b00000000 :
b00011111 ;
0<
0=
0>
b00000000 ?
b00000000 @
b00011111 A
0B
b00001010 C
#2000000
1%
1.
17
1<
#4000000
0%
0.
07
0<
#6000000
1%
1.
17
1<
#8000000
0%
0.
07
0<
#10000000
b00000010 !
1%
b00000010 *
1.
b00000010 6
17
b00000010 ;
1<
b00000010 A
#12000000
0%
0.
07
0<
#14000000
1%
1.
17
1<
#15000000
1&
1/
19
1>
#16000000
0%
0.
07
0<
#18000000
1%
1.
17
1<
#20000000
1"
0%
1+
0.
07
18
0<
#22000000
1%
b00010111 '
b00000010 (
1.
b00000010 0
b00010111 2
b00000010 4
b00010111 5
17
b00000010 :
1<
b00000010 @
b00010111 C
#24000000
0%
0.
07
0<
#25000000
0"
0+
08
#26000000
1%
1.
17
1<
#28000000
0%
0.
07
0<
#30000000
1#
1%
b00000010 )
1,
1.
b00000010 1
b00000010 3
17
1<
1=
b00000010 ?
#32000000
0%
0.
07
0<
#34000000
1%
1.
17
1<
#35000000
0#
0,
0=
#36000000
0%
0.
07
0<
#38000000
1%
1.
17
1<
#40000000
1$
0%
1-
0.
07
0<
1B
#42000000
1%
1.
17
1<
#44000000
0%
0.
07
0<
#45000000
0$
b00000010 '
0-
b00000010 2
b00000010 5
0B
b00000010 C
#46000000
1%
1.
17
1<
#48000000
0%
0.
07
0<
#50000000
1%
0&
b00001010 '
b00000000 (
b00000000 )
1.
0/
b00000000 0
b00000000 1
b00001010 2
b00000000 3
b00000000 4
b00001010 5
17
09
b00000000 :
1<
0>
b00000000 ?
b00000000 @
b00001010 C
#52000000
0%
1&
0.
1/
07
19
0<
1>
#54000000
1%
1.
17
1<
#56000000
0%
0.
07
0<
#58000000
1%
1.
17
1<
#60000000
b00000110 !
0%
b00000110 *
0.
b00000110 6
07
b00000110 ;
0<
b00000110 A
#62000000
1%
1.
17
1<
#64000000
0%
0.
07
0<
#66000000
1%
1.
17
1<
#68000000
0%
0.
07
0<
#70000000
1%
1.
17
1<
#72000000
0%
0.
07
0<
#74000000
1%
1.
17
1<
#76000000
0%
0.
07
0<
#78000000
1%
1.
17
1<
#80000000
1"
1#
1$
0%
1+
1,
1-
0.
07
18
0<
1=
1B
#82000000
1%
b00000110 (
b00000110 )
1.
b00000110 0
b00000110 1
b00000110 3
b00000110 4
17
b00000110 :
1<
b00000110 ?
b00000110 @
#84000000
0%
0.
07
0<
#85000000
0"
0#
0$
b00000110 '
0+
0,
0-
b00000110 2
b00000110 5
08
0=
0B
b00000110 C
