Billaume/TP2/multiplexeur.vhd
--Entite add
library IEEE;
use IEEE.std_logic_1164.all;

--definition de l'entite
entity multiplexeur is
	port(
		D0 : in integer;
		D1 : in integer;
		sel : in std_logic;
		S : out integer

	);
end entity;

--definition de l'architecture
architecture flot of multiplexeur is
begin
	S <= D0 when sel = '0' else D1;
end architecture;

Billaume/TP3/inverseur.vhd
--Entite add
library IEEE;
use IEEE.std_logic_1164.all;

--definition de l'entite
entity inverseur is
	generic(
		N : natural
	);

	port(
		X : in std_logic_vector(N-1 downto 0);
		S : out std_logic_vector(N-1 downto 0)

	);
end entity;

--definition de l'architecture
architecture flot of inverseur is
begin
	inverse_inst : for i in N-1 downto 0 generate
		S(i) <= not X(i);
	end generate;
		
end architecture;

Billaume/TP3/add.vhd
--Entite add
library IEEE;
use IEEE.std_logic_1164.all;

--definition de l'entite
entity add is
	port(
		A : in std_logic;
		B : in std_logic;
		Cin : in std_logic;
		S : out std_logic;
		Cout : out std_logic
	);
end entity;

--definition de l'architecture
architecture flot of add is
begin
	S <= A xor B xor Cin;
	Cout <= (A and B) or (A and Cin) or (B and Cin);
end architecture;

Billaume/TP3/addn.vhd
--Entite add
library IEEE;
use IEEE.std_logic_1164.all;

--definition de l'entite
entity addn is
	generic(
		N : natural
	);

	port(
		A : in std_logic_vector(N-1 downto 0);
		B : in std_logic_vector(N-1 downto 0);
		S : out std_logic_vector(N-1 downto 0);
		R : out std_logic
	);
end entity;

--definition de l'architecture
architecture flot of addn is

signal carry : std_logic_vector(N downto 0);
component add is
	port(
		A : in std_logic;
		B : in std_logic;
		Cin : in std_logic;
		S : out std_logic;
		Cout : out std_logic
	);
end component;

begin
	carry(0) <= '0';
	addn_inst : for i in N-1 downto 0 generate
	add_inst : add
		port map(A=>A(i),
		B=> B(i),
		Cin => carry(i), 
		S => S(i),
		Cout => Carry(i+1));
	end generate;
	R <= carry(N);
	
end architecture;

Billaume/TP3/ModifIN.vhd
--Entite add
library IEEE;
use IEEE.std_logic_1164.all;

--definition de l'entite
entity ModifIN is
	generic(
		N : natural
	);

	port(
		X : in std_logic_vector(N-1 downto 0);
		zer : in std_logic;
		neg : in std_logic;
		sorti : out std_logic_vector(N-1 downto 0)
	);
end entity;

--definition de l'architecture
architecture flot of ModifIN is

signal zero : std_logic_vector(N-1 downto 0):= (others =>'0');
signal MuxInOutput : std_logic_vector(N-1 downto 0);
signal InvOut : std_logic_vector(N-1 downto 0);
signal MuxInvOutput : std_logic_vector(N-1 downto 0);

component inverseur is
	generic(
		N : natural
	);

	port(
		X : in std_logic_vector(N-1 downto 0);
		S : out std_logic_vector(N-1 downto 0)
	);
end component;

component multiplexeur is
	generic(
		N : natural
	);
	port(
		D0 : in std_logic_vector(N-1 downto 0);
		D1 : in std_logic_vector(N-1 downto 0);
		sel : in std_logic;
		S : out std_logic_vector(N-1 downto 0)
	);
end component;
	

begin
	
	M1 : multiplexeur
	generic map(N=>N)
	port map(
		D0 => X,
		D1 => zero,
		sel => zer,
		S => MuxInOutput
		);

	inv : inverseur
	generic map(N=>N)
	port map(
		X => MuxInOutput,
		S => InvOut
		);

	M2 : multiplexeur
	generic map(N=>N)
	port map(
		D0 => MuxInOutput,
		D1 => InvOut,
		sel => neg,
		S => MuxInvOutput
		);
	
		sorti <= MuxInvOutput;
	
end architecture;

Billaume/TP3/ALU.vhd
--Entite add
library IEEE;
use IEEE.std_logic_1164.all;

--definition de l'entite
entity ALU is
	generic(
		N : natural
	);

	port(
		X : in std_logic_vector(N-1 downto 0);
		Y : in std_logic_vector(N-1 downto 0);
		zx : in std_logic;
		nx : in std_logic;
		zy : in std_logic;
		ny : in std_logic;
		f : in std_logic; 	--selecteur premier mux
		n0 : in std_logic;	--selecteur deuxieme mux
		S : out std_logic_vector(N-1 downto 0)
	);
end entity;

--definition de l'architecture
architecture flot of ALU is

signal Mod1Out : std_logic_vector(N-1 downto 0);
signal Mod2Out : std_logic_vector(N-1 downto 0);

signal ADDOut : std_logic_vector(N-1 downto 0);
signal carry : std_logic;
signal ETOut : std_logic_vector(N-1 downto 0);

signal MuxInOutput : std_logic_vector(N-1 downto 0);
signal InvOut : std_logic_vector(N-1 downto 0);
signal MuxInvOutput : std_logic_vector(N-1 downto 0);

component ModifIN is
	generic(
		N : natural
	);

	port(
		X : in std_logic_vector(N-1 downto 0);
		zer : in std_logic;
		neg : in std_logic;
		sorti : out std_logic_vector(N-1 downto 0)
	);
end component;

component multiplexeur is
	generic(
		N : natural
	);
	port(
		D0 : in std_logic_vector(N-1 downto 0);
		D1 : in std_logic_vector(N-1 downto 0);
		sel : in std_logic;
		S : out std_logic_vector(N-1 downto 0)
	);
end component;

component inverseur is
	generic(
		N : natural
	);

	port(
		X : in std_logic_vector(N-1 downto 0);
		S : out std_logic_vector(N-1 downto 0)
	);
end component;

component addn is
	generic(
		N : natural
	);

	port(
		A : in std_logic_vector(N-1 downto 0);
		B : in std_logic_vector(N-1 downto 0);
		S : out std_logic_vector(N-1 downto 0);
		R : out std_logic
	);
end component;

begin

ETOut <=  (Mod1Out and Mod2Out);
	
	Modx : ModifIN
	generic map(N=>N)
	port map(
		X => X,
		zer => zx,
		neg => nx,
		sorti => Mod1Out
		);
	
	Mody : ModifIN
	generic map(N=>N)
	port map(
		X => Y,
		zer => zy,
		neg => ny,
		sorti => Mod2Out
		);
		
	ADD : addn
	generic map(N=>N)
	port map(
		A => Mod1Out,
		B => Mod2Out,
		S => ADDOut,
		R => carry
		);
		
	M1 : multiplexeur
	generic map(N=>N)
	port map(
		D0 => ETOut,
		D1 => ADDOut,
		sel => f,
		S => MuxInOutput
		);
		
	inv : inverseur
	generic map(N=>N)
	port map(
		X => MuxInOutput,
		S => InvOut
		);
				
	M2 : multiplexeur
	generic map(N=>N)
	port map(
		D0 => MuxInOutput,
		D1 => InvOut,
		sel => n0,
		S => MuxInvOutput
		);
	
	S <= MuxInvOutput;
	
end architecture;

Billaume/TP3/Bench_ALU/bench_ALU.vhd
library IEEE;
use     IEEE.std_logic_1164.all;
use     IEEE.numeric_std.all;


-- bibliotheque indique dans votre Makefile
library TP_LIB;
use     TP_LIB.ALU;

entity bench_ALU is

end entity;

architecture str of bench_ALU is

	component ALU is
		generic(
			N : natural
		);

		port(
			X : in std_logic_vector(N-1 downto 0);
			Y : in std_logic_vector(N-1 downto 0);
			zx : in std_logic;
			nx : in std_logic;
			zy : in std_logic;
			ny : in std_logic;
			f : in std_logic; 	--selecteur premier mux
			n0 : in std_logic;	--selecteur deuxieme mux
			S : out std_logic_vector(N-1 downto 0)
		);
	end component;
	
	constant N_c : natural := 4;
	
	-- definition de signaux de test	
	signal X_S : std_logic_vector(N_c-1 downto 0):= "0011";
	signal Y_S : std_logic_vector(N_c-1 downto 0):= "0101";
	
	-- selection
	signal zx_S : std_logic:='1';
	signal nx_S : std_logic:='0';
	signal zy_S : std_logic:='1';
	signal ny_S : std_logic:='0';
	signal f_S : std_logic :='1';
	signal n0_S : std_logic:='0';
	
	-- sortie des composant
	signal SORTIE_S : std_logic_vector(N_c-1 downto 0);



begin
	ALU_test : ALU
		generic map(
		N => N_c)
		
		port map(
			X => X_S,
			Y => Y_S,
			zx => zx_S,
			nx => nx_S,
			zy => zy_S,
			ny => ny_S,
			f => f_S,
			n0 => n0_S,
			S => SORTIE_S
		);
		
	zx_S <= '0' after 15 ns,'1' after 20 ns,'0' after 25 ns,'1' after 30 ns,'0' after 35 ns,'1' after 40 ns, '0' after 45 ns,'1' after 50 ns,'0' after 55 ns,'1' after 65 ns,'0' after 70 ns;
	nx_S <= '1' after 5 ns,'0' after 15 ns,'1' after 20 ns,'0' after 25 ns,'1' after 30 ns,'0' after 35 ns,'1' after 40 ns,'0' after 55 ns,'1' after 65 ns,'0' after 75 ns,'1' after 85 ns;
	zy_S <= '0' after 20 ns,'1' after 25 ns,'0' after 30 ns,'1' after 35 ns,'0' after 40 ns,'1' after 45 ns,'0' after 50 ns,'1' after 60 ns,'0' after 65 ns;
	ny_S <= '1' after 5 ns,'0' after 10 ns,'1' after 15 ns,'0' after 20 ns,'1' after 25 ns,'0' after 30 ns,'1' after 35 ns,'0' after 40 ns,'1' after 45 ns,'0' after 55 ns,'1' after 60 ns,'0' after 65 ns,'1' after 75 ns,'0' after 80 ns,'1' after 85 ns;
	
	f_S <= '0' after 15 ns,'1' after 35 ns, '0' after 80 ns;
	n0_S <='1' after 5 ns,'0' after 10 ns,'1' after 25 ns,'0' after 55 ns,'1' after 70 ns,'0' after 80 ns,'1' after 85 ns;


end architecture;

Billaume/TP3/Bench_ALU/bench_ALU_wave.vcd
$date
  Mon Nov 30 17:10:49 2020
$end
$version
  GHDL v0
$end
$timescale
  1 fs
$end
$scope module standard $end
$upscope $end
$scope module std_logic_1164 $end
$upscope $end
$scope module numeric_std $end
$upscope $end
$scope module bench_alu $end
$var reg 4 ! x_s[3:0] $end
$var reg 4 " y_s[3:0] $end
$var reg 1 # zx_s $end
$var reg 1 $ nx_s $end
$var reg 1 % zy_s $end
$var reg 1 & ny_s $end
$var reg 1 ' f_s $end
$var reg 1 ( n0_s $end
$var reg 4 ) sortie_s[3:0] $end
$scope module alu_test $end
$var reg 4 * x[3:0] $end
$var reg 4 + y[3:0] $end
$var reg 1 , zx $end
$var reg 1 - nx $end
$var reg 1 . zy $end
$var reg 1 / ny $end
$var reg 1 0 f $end
$var reg 1 1 n0 $end
$var reg 4 2 s[3:0] $end
$var reg 4 3 mod1out[3:0] $end
$var reg 4 4 mod2out[3:0] $end
$var reg 4 5 addout[3:0] $end
$var reg 1 6 carry $end
$var reg 4 7 etout[3:0] $end
$var reg 4 8 muxinoutput[3:0] $end
$var reg 4 9 invout[3:0] $end
$var reg 4 : muxinvoutput[3:0] $end
$scope module modx $end
$var reg 4 ; x[3:0] $end
$var reg 1 < zer $end
$var reg 1 = neg $end
$var reg 4 > sorti[3:0] $end
$var reg 4 ? zero[3:0] $end
$var reg 4 @ muxinoutput[3:0] $end
$var reg 4 A invout[3:0] $end
$var reg 4 B muxinvoutput[3:0] $end
$scope module m1 $end
$var reg 4 C d0[3:0] $end
$var reg 4 D d1[3:0] $end
$var reg 1 E sel $end
$var reg 4 F s[3:0] $end
$upscope $end
$scope module inv $end
$var reg 4 G x[3:0] $end
$var reg 4 H s[3:0] $end
$scope module inverse_inst(0) $end
$upscope $end
$scope module inverse_inst(1) $end
$upscope $end
$scope module inverse_inst(2) $end
$upscope $end
$scope module inverse_inst(3) $end
$upscope $end
$upscope $end
$scope module m2 $end
$var reg 4 I d0[3:0] $end
$var reg 4 J d1[3:0] $end
$var reg 1 K sel $end
$var reg 4 L s[3:0] $end
$upscope $end
$upscope $end
$scope module mody $end
$var reg 4 M x[3:0] $end
$var reg 1 N zer $end
$var reg 1 O neg $end
$var reg 4 P sorti[3:0] $end
$var reg 4 Q zero[3:0] $end
$var reg 4 R muxinoutput[3:0] $end
$var reg 4 S invout[3:0] $end
$var reg 4 T muxinvoutput[3:0] $end
$scope module m1 $end
$var reg 4 U d0[3:0] $end
$var reg 4 V d1[3:0] $end
$var reg 1 W sel $end
$var reg 4 X s[3:0] $end
$upscope $end
$scope module inv $end
$var reg 4 Y x[3:0] $end
$var reg 4 Z s[3:0] $end
$scope module inverse_inst(0) $end
$upscope $end
$scope module inverse_inst(1) $end
$upscope $end
$scope module inverse_inst(2) $end
$upscope $end
$scope module inverse_inst(3) $end
$upscope $end
$upscope $end
$scope module m2 $end
$var reg 4 [ d0[3:0] $end
$var reg 4 \ d1[3:0] $end
$var reg 1 ] sel $end
$var reg 4 ^ s[3:0] $end
$upscope $end
$upscope $end
$scope module add $end
$var reg 4 _ a[3:0] $end
$var reg 4 ` b[3:0] $end
$var reg 4 a s[3:0] $end
$var reg 1 b r $end
$var reg 5 c carry[4:0] $end
$scope module addn_inst(0) $end
$scope module add_inst $end
$var reg 1 d a $end
$var reg 1 e b $end
$var reg 1 f cin $end
$var reg 1 g s $end
$var reg 1 h cout $end
$upscope $end
$upscope $end
$scope module addn_inst(1) $end
$scope module add_inst $end
$var reg 1 i a $end
$var reg 1 j b $end
$var reg 1 k cin $end
$var reg 1 l s $end
$var reg 1 m cout $end
$upscope $end
$upscope $end
$scope module addn_inst(2) $end
$scope module add_inst $end
$var reg 1 n a $end
$var reg 1 o b $end
$var reg 1 p cin $end
$var reg 1 q s $end
$var reg 1 r cout $end
$upscope $end
$upscope $end
$scope module addn_inst(3) $end
$scope module add_inst $end
$var reg 1 s a $end
$var reg 1 t b $end
$var reg 1 u cin $end
$var reg 1 v s $end
$var reg 1 w cout $end
$upscope $end
$upscope $end
$upscope $end
$scope module m1 $end
$var reg 4 x d0[3:0] $end
$var reg 4 y d1[3:0] $end
$var reg 1 z sel $end
$var reg 4 { s[3:0] $end
$upscope $end
$scope module inv $end
$var reg 4 | x[3:0] $end
$var reg 4 } s[3:0] $end
$scope module inverse_inst(0) $end
$upscope $end
$scope module inverse_inst(1) $end
$upscope $end
$scope module inverse_inst(2) $end
$upscope $end
$scope module inverse_inst(3) $end
$upscope $end
$upscope $end
$scope module m2 $end
$var reg 4 !" d0[3:0] $end
$var reg 4 "" d1[3:0] $end
$var reg 1 #" sel $end
$var reg 4 $" s[3:0] $end
$upscope $end
$upscope $end
$upscope $end
$enddefinitions $end
#0
b0011 !
b0101 "
1#
0$
1%
0&
1'
0(
b0000 )
b0011 *
b0101 +
1,
0-
1.
0/
10
01
b0000 2
b0000 3
b0000 4
b0000 5
06
b0000 7
b0000 8
b1111 9
b0000 :
b0011 ;
1<
0=
b0000 >
b0000 ?
b0000 @
b1111 A
b0000 B
b0011 C
b0000 D
1E
b0000 F
b0000 G
b1111 H
b0000 I
b1111 J
0K
b0000 L
b0101 M
1N
0O
b0000 P
b0000 Q
b0000 R
b1111 S
b0000 T
b0101 U
b0000 V
1W
b0000 X
b0000 Y
b1111 Z
b0000 [
b1111 \
0]
b0000 ^
b0000 _
b0000 `
b0000 a
0b
b00000 c
0d
0e
0f
0g
0h
0i
0j
0k
0l
0m
0n
0o
0p
0q
0r
0s
0t
0u
0v
0w
b0000 x
b0000 y
1z
b0000 {
b0000 |
b1111 }
b0000 !"
b1111 ""
0#"
b0000 $"
#5000000
1$
1&
1(
b0001 )
1-
1/
11
b0001 2
b1111 3
b1111 4
b1110 5
16
b1111 7
b1110 8
b0001 9
b0001 :
1=
b1111 >
b1111 B
1K
b1111 L
1O
b1111 P
b1111 T
1]
b1111 ^
b1111 _
b1111 `
b1110 a
1b
b11110 c
1d
1e
1h
1i
1j
1k
1l
1m
1n
1o
1p
1q
1r
1s
1t
1u
1v
1w
b1111 x
b1110 y
b1110 {
b1110 |
b0001 }
b1110 !"
b0001 ""
1#"
b0001 $"
#10000000
0&
0(
b1111 )
0/
01
b1111 2
b0000 4
b1111 5
06
b0000 7
b1111 8
b0000 9
b1111 :
0O
b0000 P
b0000 T
0]
b0000 ^
b0000 `
b1111 a
0b
b00000 c
0e
1g
0h
0j
0k
1l
0m
0o
0p
1q
0r
0t
0u
1v
0w
b0000 x
b1111 y
b1111 {
b1111 |
b0000 }
b1111 !"
b0000 ""
0#"
b1111 $"
#15000000
0#
0$
1&
0'
b0011 )
0,
0-
1/
00
b0011 2
b0011 3
b1111 4
b0010 5
16
b0011 7
b0011 8
b1100 9
b0011 :
0<
0=
b0011 >
b0011 @
b1100 A
b0011 B
0E
b0011 F
b0011 G
b1100 H
b0011 I
b1100 J
0K
b0011 L
1O
b1111 P
b1111 T
1]
b1111 ^
b0011 _
b1111 `
b0010 a
1b
b11110 c
1d
1e
0g
1h
1i
1j
1k
1l
1m
0n
1o
1p
0q
1r
0s
1t
1u
0v
1w
b0011 x
b0010 y
0z
b0011 {
b0011 |
b1100 }
b0011 !"
b1100 ""
b0011 $"
#20000000
1#
1$
0%
0&
b0101 )
1,
1-
0.
0/
b0101 2
b1111 3
b0101 4
b0100 5
b0101 7
b0101 8
b1010 9
b0101 :
1<
1=
b1111 >
b0000 @
b1111 A
b1111 B
1E
b0000 F
b0000 G
b1111 H
b0000 I
b1111 J
1K
b1111 L
0N
0O
b0101 P
b0101 R
b1010 S
b0101 T
0W
b0101 X
b0101 Y
b1010 Z
b0101 [
b1010 \
0]
b0101 ^
b1111 _
b0101 `
b0100 a
b11110 c
1d
1e
0g
1h
1i
0j
1k
0l
1m
1n
1o
1p
1q
1s
0t
b0101 x
b0100 y
b0101 {
b0101 |
b1010 }
b0101 !"
b1010 ""
b0101 $"
#25000000
0#
0$
1%
1&
1(
b1100 )
0,
0-
1.
1/
11
b1100 2
b0011 3
b1111 4
b0010 5
16
b0011 7
b0011 8
b1100 9
b1100 :
0<
0=
b0011 >
b0011 @
b1100 A
b0011 B
0E
b0011 F
b0011 G
b1100 H
b0011 I
b1100 J
0K
b0011 L
1N
1O
b1111 P
b0000 R
b1111 S
b1111 T
1W
b0000 X
b0000 Y
b1111 Z
b0000 [
b1111 \
1]
b1111 ^
b0011 _
b1111 `
b0010 a
1b
b11110 c
1d
1e
0g
1h
1i
1j
1k
1l
0n
1o
0q
1r
0s
1t
1u
0v
1w
b0011 x
b0010 y
b0011 {
b0011 |
b1100 }
b0011 !"
b1100 ""
1#"
b1100 $"
#30000000
1#
1$
0%
0&
b1010 )
1,
1-
0.
0/
b1010 2
b1111 3
b0101 4
b0100 5
b0101 7
b0101 8
b1010 9
b1010 :
1<
1=
b1111 >
b0000 @
b1111 A
b1111 B
1E
b0000 F
b0000 G
b1111 H
b0000 I
b1111 J
1K
b1111 L
0N
0O
b0101 P
b0101 R
b1010 S
b0101 T
0W
b0101 X
b0101 Y
b1010 Z
b0101 [
b1010 \
0]
b0101 ^
b1111 _
b0101 `
b0100 a
b11110 c
1d
1e
0g
1h
1i
0j
1k
0l
1m
1n
1o
1p
1q
1s
0t
b0101 x
b0100 y
b0101 {
b0101 |
b1010 }
b0101 !"
b1010 ""
b1010 $"
#35000000
0#
0$
1%
1&
1'
b1101 )
0,
0-
1.
1/
10
b1101 2
b0011 3
b1111 4
b0010 5
16
b0011 7
b0010 8
b1101 9
b1101 :
0<
0=
b0011 >
b0011 @
b1100 A
b0011 B
0E
b0011 F
b0011 G
b1100 H
b0011 I
b1100 J
0K
b0011 L
1N
1O
b1111 P
b0000 R
b1111 S
b1111 T
1W
b0000 X
b0000 Y
b1111 Z
b0000 [
b1111 \
1]
b1111 ^
b0011 _
b1111 `
b0010 a
1b
b11110 c
1d
1e
0g
1h
1i
1j
1k
1l
0n
1o
0q
1r
0s
1t
1u
0v
1w
b0011 x
b0010 y
1z
b0010 {
b0010 |
b1101 }
b0010 !"
b1101 ""
b1101 $"
#40000000
1#
1$
0%
0&
b1011 )
1,
1-
0.
0/
b1011 2
b1111 3
b0101 4
b0100 5
b0101 7
b0100 8
b1011 9
b1011 :
1<
1=
b1111 >
b0000 @
b1111 A
b1111 B
1E
b0000 F
b0000 G
b1111 H
b0000 I
b1111 J
1K
b1111 L
0N
0O
b0101 P
b0101 R
b1010 S
b0101 T
0W
b0101 X
b0101 Y
b1010 Z
b0101 [
b1010 \
0]
b0101 ^
b1111 _
b0101 `
b0100 a
b11110 c
1d
1e
0g
1h
1i
0j
1k
0l
1m
1n
1o
1p
1q
1s
0t
b0101 x
b0100 y
b0100 {
b0100 |
b1011 }
b0100 !"
b1011 ""
b1011 $"
#45000000
0#
1%
1&
b0100 )
0,
1.
1/
b0100 2
b1100 3
b1111 4
b1011 5
b1100 7
b1011 8
b0100 9
b0100 :
0<
b1100 >
b0011 @
b1100 A
b1100 B
0E
b0011 F
b0011 G
b1100 H
b0011 I
b1100 J
b1100 L
1N
1O
b1111 P
b0000 R
b1111 S
b1111 T
1W
b0000 X
b0000 Y
b1111 Z
b0000 [
b1111 \
1]
b1111 ^
b1100 _
b1111 `
b1011 a
b11000 c
0d
1e
1g
0h
0i
1j
0k
1l
0m
1o
0p
0q
1t
1v
b1100 x
b1011 y
b1011 {
b1011 |
b0100 }
b1011 !"
b0100 ""
b0100 $"
#50000000
1#
0%
b0110 )
1,
0.
b0110 2
b1111 3
b1010 4
b1001 5
b1010 7
b1001 8
b0110 9
b0110 :
1<
b1111 >
b0000 @
b1111 A
b1111 B
1E
b0000 F
b0000 G
b1111 H
b0000 I
b1111 J
b1111 L
0N
b1010 P
b0101 R
b1010 S
b1010 T
0W
b0101 X
b0101 Y
b1010 Z
b0101 [
b1010 \
b1010 ^
b1111 _
b1010 `
b1001 a
b11100 c
1d
0e
1i
0l
1m
0o
1p
0q
1r
1u
1v
b1010 x
b1001 y
b1001 {
b1001 |
b0110 }
b1001 !"
b0110 ""
b0110 $"
#55000000
0#
0$
0&
0(
b1000 )
0,
0-
0/
01
b1000 2
b0011 3
b0101 4
b1000 5
06
b0001 7
b1000 8
b0111 9
b1000 :
0<
0=
b0011 >
b0011 @
b1100 A
b0011 B
0E
b0011 F
b0011 G
b1100 H
b0011 I
b1100 J
0K
b0011 L
0O
b0101 P
b0101 T
0]
b0101 ^
b0011 _
b0101 `
b1000 a
0b
b01110 c
1d
1e
0g
1h
1i
0j
1k
0l
1m
0n
1o
1p
0q
1r
0s
0t
1u
1v
0w
b0001 x
b1000 y
b1000 {
b1000 |
b0111 }
b1000 !"
b0111 ""
0#"
b1000 $"
#60000000
1%
1&
b0010 )
1.
1/
b0010 2
b1111 4
b0010 5
16
b0011 7
b0010 8
b1101 9
b0010 :
1N
1O
b1111 P
b0000 R
b1111 S
b1111 T
1W
b0000 X
b0000 Y
b1111 Z
b0000 [
b1111 \
1]
b1111 ^
b1111 `
b0010 a
1b
b11110 c
1e
0g
1h
1j
1k
1l
1o
0q
1r
1t
1u
0v
1w
b0011 x
b0010 y
b0010 {
b0010 |
b1101 }
b0010 !"
b1101 ""
b0010 $"
#65000000
1#
1$
0%
0&
b0100 )
1,
1-
0.
0/
b0100 2
b1111 3
b0101 4
b0100 5
b0101 7
b0100 8
b1011 9
b0100 :
1<
1=
b1111 >
b0000 @
b1111 A
b1111 B
1E
b0000 F
b0000 G
b1111 H
b0000 I
b1111 J
1K
b1111 L
0N
0O
b0101 P
b0101 R
b1010 S
b0101 T
0W
b0101 X
b0101 Y
b1010 Z
b0101 [
b1010 \
0]
b0101 ^
b1111 _
b0101 `
b0100 a
b11110 c
1d
1e
0g
1h
1i
0j
1k
0l
1m
1n
1o
1p
1q
1s
0t
b0101 x
b0100 y
b0100 {
b0100 |
b1011 }
b0100 !"
b1011 ""
b0100 $"
#70000000
0#
1(
b1110 )
0,
11
b1110 2
b1100 3
b0001 5
b0100 7
b0001 8
b1110 9
b1110 :
0<
b1100 >
b0011 @
b1100 A
b1100 B
0E
b0011 F
b0011 G
b1100 H
b0011 I
b1100 J
b1100 L
b1100 _
b0001 a
b11000 c
0d
1g
0h
0i
0k
0l
0m
0p
0q
b0100 x
b0001 y
b0001 {
b0001 |
b1110 }
b0001 !"
b1110 ""
1#"
b1110 $"
#75000000
0$
1&
b0010 )
0-
1/
b0010 2
b0011 3
b1010 4
b1101 5
06
b0010 7
b1101 8
b0010 9
b0010 :
0=
b0011 >
b0011 B
0K
b0011 L
1O
b1010 P
b1010 T
1]
b1010 ^
b0011 _
b1010 `
b1101 a
0b
b00100 c
1d
0e
1i
1j
1m
0n
0o
1p
1q
0r
0s
1t
0u
1v
0w
b0010 x
b1101 y
b1101 {
b1101 |
b0010 }
b1101 !"
b0010 ""
b0010 $"
#80000000
0&
0'
0(
b0001 )
0/
00
01
b0001 2
b0101 4
b1000 5
b0001 7
b0001 8
b1110 9
b0001 :
0O
b0101 P
b0101 T
0]
b0101 ^
b0101 `
b1000 a
b01110 c
1e
0g
1h
0j
1k
0l
1m
1o
1p
0q
1r
0t
1u
1v
b0001 x
b1000 y
0z
b0001 {
b0001 |
b1110 }
b0001 !"
b1110 ""
0#"
b0001 $"
#85000000
1$
1&
1(
b0111 )
1-
1/
11
b0111 2
b1100 3
b1010 4
b0110 5
16
b1000 7
b1000 8
b0111 9
b0111 :
1=
b1100 >
b1100 B
1K
b1100 L
1O
b1010 P
b1010 T
1]
b1010 ^
b1100 _
b1010 `
b0110 a
1b
b10000 c
0d
0e
0h
0i
1j
0k
1l
0m
1n
0o
0p
1q
0r
1s
1t
0u
0v
1w
b1000 x
b0110 y
b1000 {
b1000 |
b0111 }
b1000 !"
b0111 ""
1#"
b0111 $"
