Billaume/TP3/add.vhd
--Entite add
library IEEE;
use IEEE.std_logic_1164.all;

--definition de l'entite
entity add is
	port(
		A : in std_logic;
		B : in std_logic;
		Cin : in std_logic;
		S : out std_logic;
		Cout : out std_logic
	);
end entity;

--definition de l'architecture
architecture flot of add is
begin
	S <= A xor B xor Cin;
	Cout <= (A and B) or (A and Cin) or (B and Cin);
end architecture;

Billaume/TP1/Bench_add/bench_add.vhd
--Aiguillage téléphonique
library IEEE;
use IEEE.std_logic_1164.all;
use IEEE.numeric_std.all;

--bibliotheque indique dans votre Makefile
library TP_LIB;
use     TP_LIB.add;

--definition de l'entite
entity bench_add is
end entity;

--definition de l'architecture de test
architecture test of bench_add is

  component add
  port(
	Cin : in std_logic;
	A : in std_logic;
	B : in std_logic;
        S : out std_logic;
        Cout : out std_logic

  );
  end component;

  --definition de signaux de test
  signal Cin_S : std_logic := '0' ;
  signal A_S : std_logic := '0' ;
  signal B_S : std_logic := '0' ;
  signal S_S : std_logic := '0' ;
  signal Cout_S : std_logic := '0' ;
  

begin

  --design under test (dut)
  dut : add
    port map(
      Cin => Cin_S,
      A => A_S,
      B => B_S,
      S => S_S,
      Cout => Cout_S
      
      
    );

  --Generation des stimulis
  A_S   <=  not A_S after 10 ns;
  B_S   <=  not B_S after 20 ns;
  Cin_S <=  not Cin_S after 30 ns;
  
end architecture;

Billaume/TP1/Bench_add/bench_add_wave.vcd
$date
  Tue Nov  3 16:41:13 2020
$end
$version
  GHDL v0
$end
$timescale
  1 fs
$end
$scope module standard $end
$upscope $end
$scope module std_logic_1164 $end
$upscope $end
$scope module numeric_std $end
$upscope $end
$scope module bench_add $end
$var reg 1 ! cin_s $end
$var reg 1 " a_s $end
$var reg 1 # b_s $end
$var reg 1 $ s_s $end
$var reg 1 % cout_s $end
$scope module dut $end
$var reg 1 & a $end
$var reg 1 ' b $end
$var reg 1 ( cin $end
$var reg 1 ) s $end
$var reg 1 * cout $end
$upscope $end
$upscope $end
$enddefinitions $end
#0
0!
0"
0#
0$
0%
0&
0'
0(
0)
0*
#10000000
1"
1$
1&
1)
#20000000
0"
1#
0&
1'
#30000000
1!
1"
1%
1&
1(
1*
#40000000
0"
0#
0%
0&
0'
0*
#50000000
1"
0$
1%
1&
0)
1*
#60000000
0!
0"
1#
1$
0%
0&
1'
0(
1)
0*
#70000000
1"
0$
1%
1&
0)
1*
#80000000
0"
0#
0%
0&
0'
0*
#90000000
1!
1"
1%
1&
1(
1*
#100000000
0"
1#
0&
1'
