Billaume/TP2/multiplexeur.vhd
--Entite add
library IEEE;
use IEEE.std_logic_1164.all;

--definition de l'entite
entity multiplexeur is
	port(
		D0 : in integer;
		D1 : in integer;
		sel : in std_logic;
		S : out integer

	);
end entity;

--definition de l'architecture
architecture flot of multiplexeur is
begin
	S <= D0 when sel = '0' else D1;
end architecture;

Billaume/TP3/inverseur.vhd
--Entite add
library IEEE;
use IEEE.std_logic_1164.all;

--definition de l'entite
entity inverseur is
	generic(
		N : natural
	);

	port(
		X : in std_logic_vector(N-1 downto 0);
		S : out std_logic_vector(N-1 downto 0)

	);
end entity;

--definition de l'architecture
architecture flot of inverseur is
begin
	inverse_inst : for i in N-1 downto 0 generate
		S(i) <= not X(i);
	end generate;
		
end architecture;

Billaume/TP3/ModifIN.vhd
--Entite add
library IEEE;
use IEEE.std_logic_1164.all;

--definition de l'entite
entity ModifIN is
	generic(
		N : natural
	);

	port(
		X : in std_logic_vector(N-1 downto 0);
		zer : in std_logic;
		neg : in std_logic;
		sorti : out std_logic_vector(N-1 downto 0)
	);
end entity;

--definition de l'architecture
architecture flot of ModifIN is

signal zero : std_logic_vector(N-1 downto 0):= (others =>'0');
signal MuxInOutput : std_logic_vector(N-1 downto 0);
signal InvOut : std_logic_vector(N-1 downto 0);
signal MuxInvOutput : std_logic_vector(N-1 downto 0);

component inverseur is
	generic(
		N : natural
	);

	port(
		X : in std_logic_vector(N-1 downto 0);
		S : out std_logic_vector(N-1 downto 0)
	);
end component;

component multiplexeur is
	generic(
		N : natural
	);
	port(
		D0 : in std_logic_vector(N-1 downto 0);
		D1 : in std_logic_vector(N-1 downto 0);
		sel : in std_logic;
		S : out std_logic_vector(N-1 downto 0)
	);
end component;
	

begin
	
	M1 : multiplexeur
	generic map(N=>N)
	port map(
		D0 => X,
		D1 => zero,
		sel => zer,
		S => MuxInOutput
		);

	inv : inverseur
	generic map(N=>N)
	port map(
		X => MuxInOutput,
		S => InvOut
		);

	M2 : multiplexeur
	generic map(N=>N)
	port map(
		D0 => MuxInOutput,
		D1 => InvOut,
		sel => neg,
		S => MuxInvOutput
		);
	
		sorti <= MuxInvOutput;
	
end architecture;

Billaume/TP3/Bench_ModifIN/bench_ModifIN.vhd
library IEEE;
use     IEEE.std_logic_1164.all;
use     IEEE.numeric_std.all;


-- bibliotheque indique dans votre Makefile
library TP_LIB;
use     TP_LIB.ModifIN;

entity bench_ModifIN is

end entity;

architecture str of bench_ModifIN is

	component ModifIN is
		generic(
			N : natural
		);

		port(
			X : in std_logic_vector(N-1 downto 0);
			zer : in std_logic;
			neg : in std_logic;
			sorti : out std_logic_vector(N-1 downto 0)
		);
	end component;
	
	constant N_c : natural := 4;
	
	-- definition de signaux de test	
	signal X_S : std_logic_vector(N_c-1 downto 0):= "0011";
	
	--selection
	signal SEL1_S : std_logic:='0';
	signal SEL2_S : std_logic:='0';
	
	-- sortie des composant
	signal SORTIE_S : std_logic_vector(N_c-1 downto 0);



begin
	ModifIN_test : ModifIN
		generic map(
		N => N_c)
		
		port map(
		X => X_S,
		zer => SEL1_S,
		neg => SEL2_S,
		sorti =>SORTIE_S
		);
		
	SEL1_S <= not SEL1_S after 10 ns;
	SEL2_S <= not SEL2_S after 20 ns;

end architecture;

Billaume/TP3/Bench_ModifIN/bench_ModifIN_wave.vcd
$date
  Mon Nov 30 14:47:13 2020
$end
$version
  GHDL v0
$end
$timescale
  1 fs
$end
$scope module standard $end
$upscope $end
$scope module std_logic_1164 $end
$upscope $end
$scope module numeric_std $end
$upscope $end
$scope module bench_modifin $end
$var reg 4 ! x_s[3:0] $end
$var reg 1 " sel1_s $end
$var reg 1 # sel2_s $end
$var reg 4 $ sortie_s[3:0] $end
$scope module modifin_test $end
$var reg 4 % x[3:0] $end
$var reg 1 & zer $end
$var reg 1 ' neg $end
$var reg 4 ( sorti[3:0] $end
$var reg 4 ) zero[3:0] $end
$var reg 4 * muxinoutput[3:0] $end
$var reg 4 + invout[3:0] $end
$var reg 4 , muxinvoutput[3:0] $end
$scope module m1 $end
$var reg 4 - d0[3:0] $end
$var reg 4 . d1[3:0] $end
$var reg 1 / sel $end
$var reg 4 0 s[3:0] $end
$upscope $end
$scope module inv $end
$var reg 4 1 x[3:0] $end
$var reg 4 2 s[3:0] $end
$scope module inverse_inst(0) $end
$upscope $end
$scope module inverse_inst(1) $end
$upscope $end
$scope module inverse_inst(2) $end
$upscope $end
$scope module inverse_inst(3) $end
$upscope $end
$upscope $end
$scope module m2 $end
$var reg 4 3 d0[3:0] $end
$var reg 4 4 d1[3:0] $end
$var reg 1 5 sel $end
$var reg 4 6 s[3:0] $end
$upscope $end
$upscope $end
$upscope $end
$enddefinitions $end
#0
b0011 !
0"
0#
b0011 $
b0011 %
0&
0'
b0011 (
b0000 )
b0011 *
b1100 +
b0011 ,
b0011 -
b0000 .
0/
b0011 0
b0011 1
b1100 2
b0011 3
b1100 4
05
b0011 6
#10000000
1"
b0000 $
1&
b0000 (
b0000 *
b1111 +
b0000 ,
1/
b0000 0
b0000 1
b1111 2
b0000 3
b1111 4
b0000 6
#20000000
0"
1#
b1100 $
0&
1'
b1100 (
b0011 *
b1100 +
b1100 ,
0/
b0011 0
b0011 1
b1100 2
b0011 3
b1100 4
15
b1100 6
#30000000
1"
b1111 $
1&
b1111 (
b0000 *
b1111 +
b1111 ,
1/
b0000 0
b0000 1
b1111 2
b0000 3
b1111 4
b1111 6
#40000000
0"
0#
b0011 $
0&
0'
b0011 (
b0011 *
b1100 +
b0011 ,
0/
b0011 0
b0011 1
b1100 2
b0011 3
b1100 4
05
b0011 6
#50000000
1"
b0000 $
1&
b0000 (
b0000 *
b1111 +
b0000 ,
1/
b0000 0
b0000 1
b1111 2
b0000 3
b1111 4
b0000 6
#60000000
0"
1#
b1100 $
0&
1'
b1100 (
b0011 *
b1100 +
b1100 ,
0/
b0011 0
b0011 1
b1100 2
b0011 3
b1100 4
15
b1100 6
#70000000
1"
b1111 $
1&
b1111 (
b0000 *
b1111 +
b1111 ,
1/
b0000 0
b0000 1
b1111 2
b0000 3
b1111 4
b1111 6
#80000000
0"
0#
b0011 $
0&
0'
b0011 (
b0011 *
b1100 +
b0011 ,
0/
b0011 0
b0011 1
b1100 2
b0011 3
b1100 4
05
b0011 6
#90000000
1"
b0000 $
1&
b0000 (
b0000 *
b1111 +
b0000 ,
1/
b0000 0
b0000 1
b1111 2
b0000 3
b1111 4
b0000 6
#100000000
0"
1#
b1100 $
0&
1'
b1100 (
b0011 *
b1100 +
b1100 ,
0/
b0011 0
b0011 1
b1100 2
b0011 3
b1100 4
15
b1100 6
