TP2/Registre/Registre.vhd
library IEEE;
use     IEEE.std_logic_1164.all;
use     IEEE.numeric_std.all;


entity Registre is
	generic(
		N : natural := 16
	);
	port(
		clk : in std_logic;
		load : in std_logic; 
		nrst : in std_logic; 
		D : in std_logic_vector (N downto 0);
		Q : out std_logic_vector (N downto 0)	  
	);
end entity;

architecture RegN of Registre is

begin

     PROCESS(clk,nrst) BEGIN
  	IF nrst='0' THEN
        	Q <=(OTHERS=>'0'); -- ou S <= "Nx0";
        ELSIF clk'event and clk='1' and load='1' THEN
        	Q <= D;
        END IF;
     END PROCESS;
	
end RegN;

TP2/Registre/tb_Registre.vhd
library IEEE;
use IEEE.std_logic_1164.all;
use IEEE.numeric_std.all;

entity tb_Registre is
end tb_Registre;

architecture tb_registre_test of tb_Registre is
	
	constant Nc:	natural := 16;

	signal sig_clk : std_logic := '0'; 
	signal sig_load : std_logic := '0';
	signal sig_nrst : std_logic := '1';
	signal sig_D : std_logic_vector (Nc downto 0);
	signal sig_Q : std_logic_vector (Nc downto 0);
 
component Registre is

	generic(
		N : natural := 16
	);

	port(
		clk : in std_logic;
		load : in std_logic; 
		nrst : in std_logic; 
		D : in std_logic_vector (N downto 0);
		Q : out std_logic_vector (N downto 0)
		 
	);

end component;

begin
	DUT : Registre
	port map(
		D => sig_D,
		Q => sig_Q,
		clk => sig_clk,
		load => sig_load,
		nrst => sig_nrst
		
	);
	
	sig_clk <= not sig_clk after 5 ns; 
	sig_load <= '1' after 15 ns, '0' after 65 ns; 
	sig_nrst <= '0' after 24 ns, '1' after 30 ns, '0' after 51 ns, '1' after 54 ns;   
	sig_D <= "11101010001010101" after 10 ns,"00001010001010101" after 30 ns ;
 
	
	
	
end architecture;

TP2/Registre/tb_Registre_wave.vcd
$date
  Mon Nov  9 21:47:36 2020
$end
$version
  GHDL v0
$end
$timescale
  1 fs
$end
$scope module standard $end
$upscope $end
$scope module std_logic_1164 $end
$upscope $end
$scope module numeric_std $end
$upscope $end
$scope module tb_registre $end
$var reg 1 ! sig_clk $end
$var reg 1 " sig_load $end
$var reg 1 # sig_nrst $end
$var reg 17 $ sig_d[16:0] $end
$var reg 17 % sig_q[16:0] $end
$scope module dut $end
$var reg 1 & clk $end
$var reg 1 ' load $end
$var reg 1 ( nrst $end
$var reg 17 ) d[16:0] $end
$var reg 17 * q[16:0] $end
$upscope $end
$upscope $end
$enddefinitions $end
#0
0!
0"
1#
bUUUUUUUUUUUUUUUUU $
bUUUUUUUUUUUUUUUUU %
0&
0'
1(
bUUUUUUUUUUUUUUUUU )
bUUUUUUUUUUUUUUUUU *
#5000000
1!
1&
#10000000
0!
b11101010001010101 $
0&
b11101010001010101 )
#15000000
1!
1"
b11101010001010101 %
1&
1'
b11101010001010101 *
#20000000
0!
0&
#24000000
0#
b00000000000000000 %
0(
b00000000000000000 *
#25000000
1!
1&
#30000000
0!
1#
b00001010001010101 $
0&
1(
b00001010001010101 )
#35000000
1!
b00001010001010101 %
1&
b00001010001010101 *
#40000000
0!
0&
#45000000
1!
1&
#50000000
0!
0&
#51000000
0#
b00000000000000000 %
0(
b00000000000000000 *
#54000000
1#
1(
#55000000
1!
b00001010001010101 %
1&
b00001010001010101 *
#60000000
0!
0&
#65000000
1!
0"
1&
0'
