Billaume/TP1/aig.vhd

library IEEE;
use     IEEE.std_logic_1164.all;

-- definition de l'entite
entity aig is
	port(
		ctl : in std_logic;
		A : in integer;
		B : in integer;
		C : out integer;
		D : out integer
	);
end entity;
-- definition de l'architecture
architecture flot of aig is
begin
	C <= A when ctl = '0' else B;
	D <= B when ctl = '0' else A;
end flot;

Billaume/TP1/res_aig.vhd

library IEEE;
use     IEEE.std_logic_1164.all;

-- definition de l'entite
entity res_aig is
	port(
		ctl : in std_logic_vector(4 downto 0);
		A : in integer;
		B : in integer;
		C : in integer;
		D : in integer;
		E : out integer;
		F : out integer;
		G : out integer;
		H : out integer
	);
end entity;

-- definition de l'architecture
architecture flot of res_aig is

component aig is
	port(
		ctl : in std_logic;
		A : in integer;
		B : in integer;
		C : out integer;
		D : out integer
	);
end component;

signal s1, s2, s3, s4, s5, s6 : integer;

begin
	aig1 : aig
		port map(
		ctl => ctl(0),
		A => A,
		B => B, 
		C => s1, 
		D => s2
		);
		
	aig2 : aig
		port map(
		ctl => ctl(1),
		A => C,
		B => D,
		C => s3, 
		D => s4
		);
		
	aig3 : aig
		port map(
		ctl => ctl(2),
		A => s1,
		B => s3,
		C => E, 
		D => s5
		);
		
	aig4 : aig
		port map(
		ctl => ctl(3),
		A => s2,
		B => s4,
		C => s6, 
		D => H
		);
		
	aig5 : aig
		port map(
		ctl => ctl(4),
		A => s5,
		B => s6,
		C => F, 
		D => G
		);
end architecture;

Billaume/TP1/Bench_res_aig/bench_res_aig.vhd
library IEEE;
use     IEEE.std_logic_1164.all;
use     IEEE.numeric_std.all;

-- bibliotheque indique dans votre Makefile
library TP_LIB;
use     TP_LIB.res_aig;

entity bench_res_aig is
end entity;

architecture str of bench_res_aig is
	component res_aig is
		port(
			ctl : in std_logic_vector(4 downto 0);
			A : in integer;
			B : in integer;
			C : in integer;
			D : in integer;
			E : out integer;
			F : out integer;
			G : out integer;
			H : out integer
		);
	end component;

	-- definition de signaux de test	
	signal A_S : integer;
	signal B_S : integer;
	signal C_S : integer;
	signal D_S : integer;
	signal E_S : integer;
	signal F_S : integer;
	signal G_S : integer;
	signal H_S : integer;
	signal ctl_S : std_logic_vector(4 downto 0):="00000";

begin
	res_aig1 : res_aig
		port map(
		ctl => ctl_S,
		A => A_S,
		B => B_S, 
		C => C_S, 
		D => D_S,
		E => E_S,
		F => F_S,
		G => G_S,
		H => H_S
		);
		

		
    A_S   <= 10;
    B_S   <= 20;	
    C_S   <= 30;
    D_S   <= 40;
    
    ctl_S(0) <= not ctl_S(0) after 10 ns;
    ctl_S(1) <= not ctl_S(1) after 20 ns;
    ctl_S(2) <= not ctl_S(2) after 40 ns;


end architecture;

Billaume/TP1/Bench_res_aig/bench_res_aig_wave.vcd
$date
  Tue Nov  3 16:30:38 2020
$end
$version
  GHDL v0
$end
$timescale
  1 fs
$end
$scope module standard $end
$upscope $end
$scope module std_logic_1164 $end
$upscope $end
$scope module numeric_std $end
$upscope $end
$scope module bench_res_aig $end
$var integer 32 ! a_s $end
$var integer 32 " b_s $end
$var integer 32 # c_s $end
$var integer 32 $ d_s $end
$var integer 32 % e_s $end
$var integer 32 & f_s $end
$var integer 32 ' g_s $end
$var integer 32 ( h_s $end
$var reg 5 ) ctl_s[4:0] $end
$scope module res_aig1 $end
$var reg 5 * ctl[4:0] $end
$var integer 32 + a $end
$var integer 32 , b $end
$var integer 32 - c $end
$var integer 32 . d $end
$var integer 32 / e $end
$var integer 32 0 f $end
$var integer 32 1 g $end
$var integer 32 2 h $end
$var integer 32 3 s1 $end
$var integer 32 4 s2 $end
$var integer 32 5 s3 $end
$var integer 32 6 s4 $end
$var integer 32 7 s5 $end
$var integer 32 8 s6 $end
$scope module aig1 $end
$var reg 1 9 ctl $end
$var integer 32 : a $end
$var integer 32 ; b $end
$var integer 32 < c $end
$var integer 32 = d $end
$upscope $end
$scope module aig2 $end
$var reg 1 > ctl $end
$var integer 32 ? a $end
$var integer 32 @ b $end
$var integer 32 A c $end
$var integer 32 B d $end
$upscope $end
$scope module aig3 $end
$var reg 1 C ctl $end
$var integer 32 D a $end
$var integer 32 E b $end
$var integer 32 F c $end
$var integer 32 G d $end
$upscope $end
$scope module aig4 $end
$var reg 1 H ctl $end
$var integer 32 I a $end
$var integer 32 J b $end
$var integer 32 K c $end
$var integer 32 L d $end
$upscope $end
$scope module aig5 $end
$var reg 1 M ctl $end
$var integer 32 N a $end
$var integer 32 O b $end
$var integer 32 P c $end
$var integer 32 Q d $end
$upscope $end
$upscope $end
$upscope $end
$enddefinitions $end
#0
b1010 !
b10100 "
b11110 #
b101000 $
b1010 %
b11110 &
b10100 '
b101000 (
b00000 )
b00000 *
b1010 +
b10100 ,
b11110 -
b101000 .
b1010 /
b11110 0
b10100 1
b101000 2
b1010 3
b10100 4
b11110 5
b101000 6
b11110 7
b10100 8
09
b1010 :
b10100 ;
b1010 <
b10100 =
0>
b11110 ?
b101000 @
b11110 A
b101000 B
0C
b1010 D
b11110 E
b1010 F
b11110 G
0H
b10100 I
b101000 J
b10100 K
b101000 L
0M
b11110 N
b10100 O
b11110 P
b10100 Q
#10000000
b10100 %
b1010 '
b00001 )
b00001 *
b10100 /
b1010 1
b10100 3
b1010 4
b1010 8
19
b10100 <
b1010 =
b10100 D
b10100 F
b1010 I
b1010 K
b1010 O
b1010 Q
#20000000
b1010 %
b101000 &
b10100 '
b11110 (
b00010 )
b00010 *
b1010 /
b101000 0
b10100 1
b11110 2
b1010 3
b10100 4
b101000 5
b11110 6
b101000 7
b10100 8
09
b1010 <
b10100 =
1>
b101000 A
b11110 B
b1010 D
b101000 E
b1010 F
b101000 G
b10100 I
b11110 J
b10100 K
b11110 L
b101000 N
b10100 O
b101000 P
b10100 Q
#30000000
b10100 %
b1010 '
b00011 )
b00011 *
b10100 /
b1010 1
b10100 3
b1010 4
b1010 8
19
b10100 <
b1010 =
b10100 D
b10100 F
b1010 I
b1010 K
b1010 O
b1010 Q
#40000000
b11110 %
b1010 &
b10100 '
b101000 (
b00100 )
b00100 *
b11110 /
b1010 0
b10100 1
b101000 2
b1010 3
b10100 4
b11110 5
b101000 6
b1010 7
b10100 8
09
b1010 <
b10100 =
0>
b11110 A
b101000 B
1C
b1010 D
b11110 E
b11110 F
b1010 G
b10100 I
b101000 J
b10100 K
b101000 L
b1010 N
b10100 O
b1010 P
b10100 Q
#50000000
b10100 &
b1010 '
b00101 )
b00101 *
b10100 0
b1010 1
b10100 3
b1010 4
b10100 7
b1010 8
19
b10100 <
b1010 =
b10100 D
b10100 G
b1010 I
b1010 K
b10100 N
b1010 O
b10100 P
b1010 Q
#60000000
b101000 %
b1010 &
b10100 '
b11110 (
b00110 )
b00110 *
b101000 /
b1010 0
b10100 1
b11110 2
b1010 3
b10100 4
b101000 5
b11110 6
b1010 7
b10100 8
09
b1010 <
b10100 =
1>
b101000 A
b11110 B
b1010 D
b101000 E
b101000 F
b1010 G
b10100 I
b11110 J
b10100 K
b11110 L
b1010 N
b10100 O
b1010 P
b10100 Q
#70000000
b10100 &
b1010 '
b00111 )
b00111 *
b10100 0
b1010 1
b10100 3
b1010 4
b10100 7
b1010 8
19
b10100 <
b1010 =
b10100 D
b10100 G
b1010 I
b1010 K
b10100 N
b1010 O
b10100 P
b1010 Q
#80000000
b1010 %
b11110 &
b10100 '
b101000 (
b00000 )
b00000 *
b1010 /
b11110 0
b10100 1
b101000 2
b1010 3
b10100 4
b11110 5
b101000 6
b11110 7
b10100 8
09
b1010 <
b10100 =
0>
b11110 A
b101000 B
0C
b1010 D
b11110 E
b1010 F
b11110 G
b10100 I
b101000 J
b10100 K
b101000 L
b11110 N
b10100 O
b11110 P
b10100 Q
#90000000
b10100 %
b1010 '
b00001 )
b00001 *
b10100 /
b1010 1
b10100 3
b1010 4
b1010 8
19
b10100 <
b1010 =
b10100 D
b10100 F
b1010 I
b1010 K
b1010 O
b1010 Q
#100000000
b1010 %
b101000 &
b10100 '
b11110 (
b00010 )
b00010 *
b1010 /
b101000 0
b10100 1
b11110 2
b1010 3
b10100 4
b101000 5
b11110 6
b101000 7
b10100 8
09
b1010 <
b10100 =
1>
b101000 A
b11110 B
b1010 D
b101000 E
b1010 F
b101000 G
b10100 I
b11110 J
b10100 K
b11110 L
b101000 N
b10100 O
b101000 P
b10100 Q
