Billaume/TP3/RAM.vhd
library IEEE;
use IEEE.std_logic_textio.all;
use IEEE.std_logic_1164.all;
use IEEE.std_logic_unsigned.all;
use IEEE.std_logic_arith.all;
use std.textio.all;

entity RAM is
	generic(
		load_file_name : string;
		dta : integer := 8;
		adr : integer := 4);
		
	port(
		address : in std_logic_vector(adr-1 downto 0);
		datain : in std_logic_vector(dta-1 downto 0);
		wr_ena : in std_logic;
		dataout : out std_logic_vector(dta-1 downto 0));
end RAM;

architecture beh of RAM is
	begin
		p_init_mem : process
			subtype myword is std_logic_vector(0 to datain'length-1);
			type storage_array is
				array ( natural range 0 to 2**address'length-1) of myword;
		
			variable storage : storage_array;
			variable index : natural;
			variable mem_data : line;
			variable vdata : integer;
			file load_file : text is load_file_name;
		
			begin
				index := 0;
				while not endfile(load_file) loop
					readline(load_file, mem_data);
					if mem_data'length > 0 then
						read(mem_data, vdata);
						storage(index):= std_logic_vector(conv_unsigned(vdata,datain'length));
						index := index +1;
					end if;
					if(index = 2**address'length) then
						index :=0;
					end if;
				end loop;
			
				loop
				 wait on address,wr_ena,datain;
				 	if wr_ena = '0' then
				 		index := conv_integer(unsigned(address));
				 		dataout <= std_logic_vector(storage(index));
			 		else
			 			index :=conv_integer(unsigned(address));
			 			storage(index) := datain;
		 			end if;
 				end loop;
		end process;
end beh;

Billaume/TP3/Bench_RAM/bench_RAM.vhd
library ieee;
use ieee.std_logic_textio.all;
use ieee.std_logic_1164.all;
use ieee.std_logic_unsigned.all;
use ieee.std_logic_arith.all;
use std.textio.all;


-- bibliotheque indique dans votre Makefile
library TP_LIB;
use     TP_LIB.RAM;

entity bench_RAM is

end entity;

architecture str of bench_RAM is

	component RAM is
		generic(
			load_file_name : string;
			dta : integer := 8;
			adr : integer := 4);
		
		port(
			address : in std_logic_vector(adr-1 downto 0);
			datain : in std_logic_vector(dta-1 downto 0);
			wr_ena : in std_logic;
			dataout : out std_logic_vector(dta-1 downto 0));
	end component;
	
	constant load_file_name_C : string := "monFichier.txt";
	constant dta_c : integer := 8;
	constant adr_c : integer := 4;
	-- definition de signaux de test	
	signal address_S : std_logic_vector(adr_c-1 downto 0):= "0000";
	signal datain_S : std_logic_vector(dta_c-1 downto 0):= "00000000";

	
	--selection
	signal wr_ena_S : std_logic := '0';
	-- sortie des composant
	signal dataout_S : std_logic_vector(dta_c-1 downto 0);



begin
	RAM_test : RAM
		generic map(
		load_file_name => load_file_name_C,
		dta => dta_C,
		adr => adr_C)
		
	
		port map(
		address => address_S,
		datain => datain_S,
		wr_ena => wr_ena_S,
		dataout => dataout_S
		);
		
	--wr_ena_S <= not wr_ena_S after 2 ns, '0' after 35 ns;
	address_S <= "0001" after 10 ns, "0010" after 20 ns , "0011" after 30 ns , "0000" after 40 ns , "0000" after 50 ns, "0001" after 60 ns, "0010" after 70 ns , "0011" after 80 ns;
	--datain_S <= "00000001" after 10 ns,"00000100" after 20 ns,"00110100" after 30 ns;
	

end architecture;

Billaume/TP3/Bench_RAM/bench_RAM_wave.vcd
$date
  Mon Dec 14 13:51:39 2020
$end
$version
  GHDL v0
$end
$timescale
  1 fs
$end
$scope module standard $end
$upscope $end
$scope module textio $end
$upscope $end
$scope module std_logic_1164 $end
$upscope $end
$scope module std_logic_textio $end
$upscope $end
$scope module std_logic_arith $end
$upscope $end
$scope module std_logic_unsigned $end
$upscope $end
$scope module bench_ram $end
$var reg 4 ! address_s[3:0] $end
$var reg 8 " datain_s[7:0] $end
$var reg 1 # wr_ena_s $end
$var reg 8 $ dataout_s[7:0] $end
$scope module ram_test $end
$var reg 4 % address[3:0] $end
$var reg 8 & datain[7:0] $end
$var reg 1 ' wr_ena $end
$var reg 8 ( dataout[7:0] $end
$upscope $end
$upscope $end
$enddefinitions $end
#0
b0000 !
b00000000 "
0#
bUUUUUUUU $
b0000 %
b00000000 &
0'
bUUUUUUUU (
#10000000
b0001 !
b00000010 $
b0001 %
b00000010 (
#20000000
b0010 !
b00000011 $
b0010 %
b00000011 (
#30000000
b0011 !
b00000100 $
b0011 %
b00000100 (
#40000000
b0000 !
b00000001 $
b0000 %
b00000001 (
#50000000
#60000000
b0001 !
b00000010 $
b0001 %
b00000010 (
#70000000
b0010 !
b00000011 $
b0010 %
b00000011 (
#80000000
b0011 !
b00000100 $
b0011 %
b00000100 (
