Billaume/TP4/Condition.vhd
library IEEE;
use IEEE.std_logic_textio.all;
use IEEE.std_logic_1164.all;
use IEEE.std_logic_unsigned.all;
use IEEE.std_logic_arith.all;
use std.textio.all;

entity Condition is
	generic(
		N : natural
	);	
	port(
		Xin : in std_logic_vector(N-1 downto 0);
		lt : in std_logic;
		eq : in std_logic;
		gt : in std_logic;
		jmp : out std_logic);
	
end entity;

architecture beh of Condition is
signal isneg : std_logic;
signal iszero : std_logic;

begin
	iszero <= '1' when conv_integer(Xin) = 0 else '0';
	isneg <= '1' when Xin(N-1) = '1' else '0';
	jmp <= (not(iszero xor isneg) and gt) or (eq and iszero) or (lt and isneg);
	
end beh;

Billaume/TP4/Bench_Condition/bench_Condition.vhd
library ieee;
use ieee.std_logic_textio.all;
use ieee.std_logic_1164.all;
use ieee.std_logic_unsigned.all;
use ieee.std_logic_arith.all;
use std.textio.all;


-- bibliotheque indique dans votre Makefile
library TP_LIB;
use     TP_LIB.Condition;

entity bench_Condition is

end entity;

architecture str of bench_Condition is

	component Condition is
		generic(
			N : natural
		);
		port(
			Xin : in std_logic_vector(N-1 downto 0);
			lt : in std_logic;
			eq : in std_logic;
			gt : in std_logic;
			jmp : out std_logic);

	end component;
	
	constant N_c : natural := 5;
	-- definition de signaux de test	
	signal Xin_S : std_logic_vector(N_c -1 downto 0):= "01111";

	
	-- sortie des composant
	signal lt_S : std_logic := '0';
	signal eq_S : std_logic := '0';
	signal gt_S : std_logic := '0';
	signal jmp_S : std_logic;


begin
	Condition_test : Condition
		generic map(N => N_c)
		port map(
			Xin => Xin_S,
			lt => lt_S,
			eq =>eq_S,
			gt =>gt_S,
			jmp => jmp_S
		);
		
	Xin_S <= "00000" after 16 ns , "10101" after 32 ns ,"00101" after 48 ns ;
	gt_S <=  not gt_S after 2 ns;
	eq_S <=  not eq_S after 4 ns;
	lt_S <=  not lt_S after 8 ns;


end architecture;

Billaume/TP4/Bench_Condition/bench_Condition_wave.vcd
$date
  Mon Dec 14 19:28:54 2020
$end
$version
  GHDL v0
$end
$timescale
  1 fs
$end
$scope module standard $end
$upscope $end
$scope module textio $end
$upscope $end
$scope module std_logic_1164 $end
$upscope $end
$scope module std_logic_textio $end
$upscope $end
$scope module std_logic_arith $end
$upscope $end
$scope module std_logic_unsigned $end
$upscope $end
$scope module bench_condition $end
$var reg 5 ! xin_s[4:0] $end
$var reg 1 " lt_s $end
$var reg 1 # eq_s $end
$var reg 1 $ gt_s $end
$var reg 1 % jmp_s $end
$scope module condition_test $end
$var reg 5 & xin[4:0] $end
$var reg 1 ' lt $end
$var reg 1 ( eq $end
$var reg 1 ) gt $end
$var reg 1 * jmp $end
$var reg 1 + isneg $end
$var reg 1 , iszero $end
$upscope $end
$upscope $end
$enddefinitions $end
#0
b01111 !
0"
0#
0$
0%
b01111 &
0'
0(
0)
0*
0+
0,
#2000000
1$
1%
1)
1*
#4000000
1#
0$
0%
1(
0)
0*
#6000000
1$
1%
1)
1*
#8000000
1"
0#
0$
0%
1'
0(
0)
0*
#10000000
1$
1%
1)
1*
#12000000
1#
0$
0%
1(
0)
0*
#14000000
1$
1%
1)
1*
#16000000
b00000 !
0"
0#
0$
0%
b00000 &
0'
0(
0)
0*
1,
#18000000
1$
1)
#20000000
1#
0$
1%
1(
0)
1*
#22000000
1$
1)
#24000000
1"
0#
0$
0%
1'
0(
0)
0*
#26000000
1$
1)
#28000000
1#
0$
1%
1(
0)
1*
#30000000
1$
1)
#32000000
b10101 !
0"
0#
0$
0%
b10101 &
0'
0(
0)
0*
1+
0,
#34000000
1$
1)
#36000000
1#
0$
1(
0)
#38000000
1$
1)
#40000000
1"
0#
0$
1%
1'
0(
0)
1*
#42000000
1$
1)
#44000000
1#
0$
1(
0)
#46000000
1$
1)
#48000000
b00101 !
0"
0#
0$
0%
b00101 &
0'
0(
0)
0*
0+
#50000000
1$
1%
1)
1*
#52000000
1#
0$
0%
1(
0)
0*
#54000000
1$
1%
1)
1*
#56000000
1"
0#
0$
0%
1'
0(
0)
0*
#58000000
1$
1%
1)
1*
#60000000
1#
0$
0%
1(
0)
0*
#62000000
1$
1%
1)
1*
#64000000
0"
0#
0$
0%
0'
0(
0)
0*
#66000000
1$
1%
1)
1*
#68000000
1#
0$
0%
1(
0)
0*
#70000000
1$
1%
1)
1*
#72000000
1"
0#
0$
0%
1'
0(
0)
0*
#74000000
1$
1%
1)
1*
#76000000
1#
0$
0%
1(
0)
0*
#78000000
1$
1%
1)
1*
#80000000
0"
0#
0$
0%
0'
0(
0)
0*
#82000000
1$
1%
1)
1*
#84000000
1#
0$
0%
1(
0)
0*
#86000000
1$
1%
1)
1*
#88000000
1"
0#
0$
0%
1'
0(
0)
0*
#90000000
1$
1%
1)
1*
#92000000
1#
0$
0%
1(
0)
0*
#94000000
1$
1%
1)
1*
#96000000
0"
0#
0$
0%
0'
0(
0)
0*
#98000000
1$
1%
1)
1*
#100000000
1#
0$
0%
1(
0)
0*
