Billaume/TP3/inverseur.vhd
--Entite add
library IEEE;
use IEEE.std_logic_1164.all;

--definition de l'entite
entity inverseur is
	generic(
		N : natural
	);

	port(
		X : in std_logic_vector(N-1 downto 0);
		S : out std_logic_vector(N-1 downto 0)

	);
end entity;

--definition de l'architecture
architecture flot of inverseur is
begin
	inverse_inst : for i in N-1 downto 0 generate
		S(i) <= not X(i);
	end generate;
		
end architecture;

Billaume/TP2/Bench_inverseur/bench_inverseur.vhd
--Aiguillage téléphonique
library IEEE;
use IEEE.std_logic_1164.all;
use IEEE.numeric_std.all;

--bibliotheque indique dans votre Makefile
library TP_LIB;
use     TP_LIB.inverseur;

--definition de l'entite
entity bench_inverseur is
end entity;

--definition de l'architecture de test
architecture test of bench_inverseur is

  component inverseur
	generic(
		N : natural
	);

	port(
		X : in std_logic_vector(N-1 downto 0);
		S : out std_logic_vector(N-1 downto 0)

	);
  end component;

  constant N_c : natural :=4;
  --definition de signaux de test
  
  signal X_S : std_logic_vector(N_c-1 downto 0);
  signal S_S : std_logic_vector(N_c-1 downto 0);
  signal X_U : unsigned(N_c -1 downto 0):= (others =>'0');
  
  begin
  
    --design under test (dut)
  dut : inverseur
    generic map(
    N => N_c)
    port map(
	X => X_S,
	S => S_S 
    );

  addition: process
  	begin
	X_U <= X_U +1;
	wait for 5 ns;
	end process;
	X_S <= std_logic_vector(X_U);
  
end architecture;

Billaume/TP2/Bench_inverseur/bench_inverseur_wave.vcd
$date
  Tue Nov 17 16:36:11 2020
$end
$version
  GHDL v0
$end
$timescale
  1 fs
$end
$scope module standard $end
$upscope $end
$scope module std_logic_1164 $end
$upscope $end
$scope module numeric_std $end
$upscope $end
$scope module bench_inverseur $end
$var reg 4 ! x_s[3:0] $end
$var reg 4 " s_s[3:0] $end
$var reg 4 # x_u[3:0] $end
$scope module dut $end
$var reg 4 $ x[3:0] $end
$var reg 4 % s[3:0] $end
$scope module inverse_inst(0) $end
$upscope $end
$scope module inverse_inst(1) $end
$upscope $end
$scope module inverse_inst(2) $end
$upscope $end
$scope module inverse_inst(3) $end
$upscope $end
$upscope $end
$upscope $end
$enddefinitions $end
#0
b0001 !
b1110 "
b0001 #
b0001 $
b1110 %
#5000000
b0010 !
b1101 "
b0010 #
b0010 $
b1101 %
#10000000
b0011 !
b1100 "
b0011 #
b0011 $
b1100 %
#15000000
b0100 !
b1011 "
b0100 #
b0100 $
b1011 %
#20000000
b0101 !
b1010 "
b0101 #
b0101 $
b1010 %
#25000000
b0110 !
b1001 "
b0110 #
b0110 $
b1001 %
#30000000
b0111 !
b1000 "
b0111 #
b0111 $
b1000 %
#35000000
b1000 !
b0111 "
b1000 #
b1000 $
b0111 %
#40000000
b1001 !
b0110 "
b1001 #
b1001 $
b0110 %
#45000000
b1010 !
b0101 "
b1010 #
b1010 $
b0101 %
#50000000
b1011 !
b0100 "
b1011 #
b1011 $
b0100 %
#55000000
b1100 !
b0011 "
b1100 #
b1100 $
b0011 %
#60000000
b1101 !
b0010 "
b1101 #
b1101 $
b0010 %
#65000000
b1110 !
b0001 "
b1110 #
b1110 $
b0001 %
#70000000
b1111 !
b0000 "
b1111 #
b1111 $
b0000 %
#75000000
b0000 !
b1111 "
b0000 #
b0000 $
b1111 %
#80000000
b0001 !
b1110 "
b0001 #
b0001 $
b1110 %
#85000000
b0010 !
b1101 "
b0010 #
b0010 $
b1101 %
#90000000
b0011 !
b1100 "
b0011 #
b0011 $
b1100 %
#95000000
b0100 !
b1011 "
b0100 #
b0100 $
b1011 %
#100000000
b0101 !
b1010 "
b0101 #
b0101 $
b1010 %
