Billaume/TP1/alarme.vhd
--Entite add
library IEEE;
use IEEE.std_logic_1164.all;

--definition de l'entite
entity alarme is
	port(
		V : in std_logic;
		P : in std_logic;
		F : in std_logic;
		S : out std_logic
	);
end entity;

--definition de l'architecture
architecture flot of alarme is
begin
	S <= V and (P or F);
	
end architecture;

Billaume/TP1/Bench_alarme/bench_alarme.vhd
--Aiguillage téléphonique
library IEEE;
use IEEE.std_logic_1164.all;
use IEEE.numeric_std.all;

--bibliotheque indique dans votre Makefile
library TP_LIB;
use     TP_LIB.alarme;

--definition de l'entite
entity bench_alarme is
end entity;

--definition de l'architecture de test
architecture test of bench_alarme is

  component alarme
	port(
		V : in std_logic;
		P : in std_logic;
		F : in std_logic;
		S : out std_logic
	);
  end component;

  --definition de signaux de test

  signal V_S : std_logic := '0' ;
  signal P_S : std_logic := '0' ;
  signal F_S : std_logic := '0' ;
  signal S_S : std_logic := '0' ;
  

begin

  --design under test (dut)
  dut : alarme
    port map(
      V => V_S,
      F => F_S,
      P => P_S,
      S => S_S
      
      
    );

  --Generation des stimulis
  V_S   <=  not V_S after 40 ns;
  P_S   <=  not P_S after 20 ns;
  F_S <=  not F_S after 10 ns;
  
end architecture;

Billaume/TP1/Bench_alarme/bench_alarme_wave.vcd
$date
  Wed Nov  4 14:16:51 2020
$end
$version
  GHDL v0
$end
$timescale
  1 fs
$end
$scope module standard $end
$upscope $end
$scope module std_logic_1164 $end
$upscope $end
$scope module numeric_std $end
$upscope $end
$scope module bench_alarme $end
$var reg 1 ! v_s $end
$var reg 1 " p_s $end
$var reg 1 # f_s $end
$var reg 1 $ s_s $end
$scope module dut $end
$var reg 1 % v $end
$var reg 1 & p $end
$var reg 1 ' f $end
$var reg 1 ( s $end
$upscope $end
$upscope $end
$enddefinitions $end
#0
0!
0"
0#
0$
0%
0&
0'
0(
#10000000
1#
1'
#20000000
1"
0#
1&
0'
#30000000
1#
1'
#40000000
1!
0"
0#
1%
0&
0'
#50000000
1#
1$
1'
1(
#60000000
1"
0#
1&
0'
#70000000
1#
1'
#80000000
0!
0"
0#
0$
0%
0&
0'
0(
#90000000
1#
1'
#100000000
1"
0#
1&
0'
