Billaume/TP1/sub.vhd
--Entite add
library IEEE;
use IEEE.std_logic_1164.all;

--definition de l'entite
entity sub is
	port(
		A : in std_logic;
		B : in std_logic;
		Cin : in std_logic;
		S : out std_logic;
		Cout : out std_logic
	);
end entity;

--definition de l'architecture
architecture flot of sub is
begin
	S <= A xor B xor Cin;
	Cout <= (not A and B) or (not A and Cin) or (B and Cin);
end architecture;

Billaume/TP1/subn.vhd
--Entite add
library IEEE;
use IEEE.std_logic_1164.all;

--definition de l'entite
entity subn is
	generic(
		N : natural
	);

	port(
		A : in std_logic_vector(N-1 downto 0);
		B : in std_logic_vector(N-1 downto 0);
		S : out std_logic_vector(N-1 downto 0);
		R : out std_logic
	);
end entity;

--definition de l'architecture
architecture flot of subn is

signal carry : std_logic_vector(N downto 0);
component sub is
	port(
		A : in std_logic;
		B : in std_logic;
		Cin : in std_logic;
		S : out std_logic;
		Cout : out std_logic
	);
end component;

begin
	carry(0) <= '0';
	subn_inst : for i in N-1 downto 0 generate
	sub_inst : sub
		port map(A=>A(i),
		B=> B(i),
		Cin => carry(i), 
		S => S(i),
		Cout => Carry(i+1));
	end generate;
	R <= carry(N);
	
end architecture;

Billaume/TP1/Bench_subn/bench_subn.vhd
library IEEE;
use     IEEE.std_logic_1164.all;
use     IEEE.numeric_std.all;


-- bibliotheque indique dans votre Makefile
library TP_LIB;
use     TP_LIB.subn;

entity bench_subn is

end entity;

architecture str of bench_subn is

	component subn is
		generic(
		N : natural
			);

		port(
			A : in std_logic_vector(N-1 downto 0);
			B : in std_logic_vector(N-1 downto 0);
			S : out std_logic_vector(N-1 downto 0);
			R : out std_logic
		);
	end component;
	
	constant N_c : natural := 4;
	
	-- definition de signaux de test	
	signal A_S : std_logic_vector(N_c-1 downto 0):= "0000";
	signal B_U : unsigned(N_c -1 downto 0):= (others =>'0');
	signal B_S : std_logic_vector(N_c-1 downto 0);
	signal R_S : std_logic;
	signal S_S : std_logic_vector(N_c-1 downto 0);


begin
	subn1 : subn
		generic map(
		N => N_c)
		
		port map(
		A => A_S,
		B => B_S,
		S => S_S,
		R => R_S
		);
		
	--pour incrementer la valeur de A_S toutes les 5 ns
	increment: process
	begin
	B_U <= B_U +1;
	wait for 5 ns;
	end process;
	B_S <= std_logic_vector(B_U);
		
    	A_S   <= "0110";	

 

end architecture;

Billaume/TP1/Bench_subn/bench_subn_wave.vcd
$date
  Wed Nov  4 14:04:01 2020
$end
$version
  GHDL v0
$end
$timescale
  1 fs
$end
$scope module standard $end
$upscope $end
$scope module std_logic_1164 $end
$upscope $end
$scope module numeric_std $end
$upscope $end
$scope module bench_subn $end
$var reg 4 ! a_s[3:0] $end
$var reg 4 " b_u[3:0] $end
$var reg 4 # b_s[3:0] $end
$var reg 1 $ r_s $end
$var reg 4 % s_s[3:0] $end
$scope module subn1 $end
$var reg 4 & a[3:0] $end
$var reg 4 ' b[3:0] $end
$var reg 4 ( s[3:0] $end
$var reg 1 ) r $end
$var reg 5 * carry[4:0] $end
$scope module subn_inst(0) $end
$scope module sub_inst $end
$var reg 1 + a $end
$var reg 1 , b $end
$var reg 1 - cin $end
$var reg 1 . s $end
$var reg 1 / cout $end
$upscope $end
$upscope $end
$scope module subn_inst(1) $end
$scope module sub_inst $end
$var reg 1 0 a $end
$var reg 1 1 b $end
$var reg 1 2 cin $end
$var reg 1 3 s $end
$var reg 1 4 cout $end
$upscope $end
$upscope $end
$scope module subn_inst(2) $end
$scope module sub_inst $end
$var reg 1 5 a $end
$var reg 1 6 b $end
$var reg 1 7 cin $end
$var reg 1 8 s $end
$var reg 1 9 cout $end
$upscope $end
$upscope $end
$scope module subn_inst(3) $end
$scope module sub_inst $end
$var reg 1 : a $end
$var reg 1 ; b $end
$var reg 1 < cin $end
$var reg 1 = s $end
$var reg 1 > cout $end
$upscope $end
$upscope $end
$upscope $end
$upscope $end
$enddefinitions $end
#0
b0110 !
b0001 "
b0001 #
0$
b0101 %
b0110 &
b0001 '
b0101 (
0)
b00010 *
0+
1,
0-
1.
1/
10
01
12
03
04
15
06
07
18
09
0:
0;
0<
0=
0>
#5000000
b0010 "
b0010 #
b0100 %
b0010 '
b0100 (
b00000 *
0,
0.
0/
11
02
03
04
07
18
#10000000
b0011 "
b0011 #
b0011 %
b0011 '
b0011 (
b00110 *
1,
1.
1/
12
13
14
17
08
#15000000
b0100 "
b0100 #
0$
b0010 %
b0100 '
b0010 (
0)
b00000 *
0,
0.
0/
01
02
13
04
16
07
08
09
0<
0=
0>
#20000000
b0101 "
b0101 #
b0001 %
b0101 '
b0001 (
b00010 *
1,
1.
1/
12
03
#25000000
b0110 "
b0110 #
0$
b0000 %
b0110 '
b0000 (
0)
b00000 *
0,
0.
0/
11
02
03
04
07
08
09
0<
0=
0>
#30000000
b0111 "
b0111 #
1$
b1111 %
b0111 '
b1111 (
1)
b11110 *
1,
1.
1/
12
13
14
17
18
19
1<
1=
1>
#35000000
b1000 "
b1000 #
b1110 %
b1000 '
b1110 (
b10000 *
0,
0.
0/
01
02
13
04
06
07
18
09
1;
0<
1=
#40000000
b1001 "
b1001 #
b1101 %
b1001 '
b1101 (
b10010 *
1,
1.
1/
12
03
#45000000
b1010 "
b1010 #
b1100 %
b1010 '
b1100 (
b10000 *
0,
0.
0/
11
02
03
04
07
18
#50000000
b1011 "
b1011 #
b1011 %
b1011 '
b1011 (
b10110 *
1,
1.
1/
12
13
14
17
08
#55000000
b1100 "
b1100 #
b1010 %
b1100 '
b1010 (
b10000 *
0,
0.
0/
01
02
13
04
16
07
08
09
0<
1=
#60000000
b1101 "
b1101 #
b1001 %
b1101 '
b1001 (
b10010 *
1,
1.
1/
12
03
#65000000
b1110 "
b1110 #
b1000 %
b1110 '
b1000 (
b10000 *
0,
0.
0/
11
02
03
04
07
08
09
0<
1=
#70000000
b1111 "
b1111 #
b0111 %
b1111 '
b0111 (
b11110 *
1,
1.
1/
12
13
14
17
18
19
1<
0=
#75000000
b0000 "
b0000 #
0$
b0110 %
b0000 '
b0110 (
0)
b00000 *
0,
0.
0/
01
02
13
04
06
07
18
09
0;
0<
0=
0>
#80000000
b0001 "
b0001 #
b0101 %
b0001 '
b0101 (
b00010 *
1,
1.
1/
12
03
#85000000
b0010 "
b0010 #
b0100 %
b0010 '
b0100 (
b00000 *
0,
0.
0/
11
02
03
04
07
18
#90000000
b0011 "
b0011 #
b0011 %
b0011 '
b0011 (
b00110 *
1,
1.
1/
12
13
14
17
08
#95000000
b0100 "
b0100 #
0$
b0010 %
b0100 '
b0010 (
0)
b00000 *
0,
0.
0/
01
02
13
04
16
07
08
09
0<
0=
0>
#100000000
b0101 "
b0101 #
b0001 %
b0101 '
b0001 (
b00010 *
1,
1.
1/
12
03
